Workbook
Name Cost_Input: 'Investor-Inputs'!$N$19
Name Cost_Map: 'Investor-Inputs'!$M$11:$N$14
Name Cost_Weight: 'Investor-Inputs'!$N$27
Name Input: 'Investor-Inputs'!$G$23
Name Investor_Map: 'Investor-Inputs'!$G$11:$H$14
Name Return_Input: 'Investor-Inputs'!$J$19
Name Return_Map: 'Investor-Inputs'!$J$11:$K$14
Name Return_Weight: 'Investor-Inputs'!$J$27
Name SIP_Input: 'Investor-Inputs'!$G$19
Name SIP_Weight: 'Investor-Inputs'!$G$27
Name SIPInput: 'Investor-Inputs'!$G$20

Sheet Investor-Inputs
H3: Investor Profiling and Fund Recommendation as per User Requirements
A7: User Inputs | D7: Select your options
B8: Select Investor Type: | D8: Conservative
B9: Select Retrun Priority | D9: Medium
B10: Select Cost Sensitivity: | D10: High | G10: Investor Type | J10: Return Priority | M10: Cost Sensitivity
G11: Investor Type | H11: Value | J11: Return Priority | K11: Value | M11: Cost | N11: Value
G12: Conservative | H12: 3 | J12: Low | K12: 1 | M12: Low | N12: 3
G13: Moderate | H13: 2 | J13: Medium | K13: 2 | M13: Medium | N13: 2
G14: Aggressive | H14: 1 | J14: High | K14: 3 | M14: High | N14: 1
A19: Calculations | D19: Value Mapping as per Investor | G19: =VLOOKUP(D8,G12:H14,2,FALSE) -> 3 | J19: =VLOOKUP(D9,J12:K14,2,FALSE) -> 2 | N19: =VLOOKUP(D10,M12:N14,2,FALSE) -> 1
D23: Total Value | G23: =SIP_Input+Return_Input+Cost_Input -> 6
D27: Normalized Value | G27: =SIP_Input/Input -> 0.5 | J27: =Return_Input/Input -> 0.33333333 | N27: =Cost_Input/Input -> 0.16666667
A29: Recommendations
B31: See next page for mutual fund recommendations based on user inputs (See the fina column Ranks)
B33: See last page for top 10 funds based on user inputs (Visual Analysis)

Sheet mutual-funds
C6: Fund Name | D6: Rating | E6: VR Opinion | F6: Category | G6: 1 Year Returns (%) | H6: 1 Year SIP Returns (%) | I6: 3 Year Returns (%) | J6: 3 Year SIP Returns (%) | K6: 5 Year Returns (%) | L6: 5 Year SIP Returns (%) | M6: Expense Ratio (%) | N6: Riskometer | O6: Return Grade | P6: Plan | Q6: ReturnScore | R6: SIPScore | S6: CostScore | T6: MFScore | U6: Rank
C7: Aditya Birla Sun Life Large Cap Fund - Regular Plan | D7: 4 | E7: Unlock | F7: Equity: Large Cap | G7: -0.47 | H7: -6.31 | I7: 13.07 | J7: 5.14 | K7: 12.5 | L7: 9.15 | M7: 1.58 | N7: Very High | O7: Above Avg. | P7: Direct | Q7: =I7*0.4+K7*0.5 -> 11.478 | R7: =(L7+J7)/2 -> 7.145 | S7: =(M7+K7)/2 -> 7.04 | T7: =('Investor-Inputs'!$G$19 * Q7) + ('Investor-Inputs'!$J$19 * R7) + ('Investor-Inputs'!$N$19 * S7) -> 55.764 | U7: =_xlfn.RANK.EQ(T7,$T$7:$T$592,0) -> 256
C8: Aditya Birla Sun Life Nifty 50 Equal Weight Index Fund - Regular Plan | D8: 4 | E8: Unlock | F8: Equity: Large Cap | G8: 6.69 | H8: 2.58 | I8: 15.81 | J8: 8.65 | M8: 1.1 | N8: Very High | O8: Above Avg. | P8: Direct | Q8: =I8*0.4+K8*0.5 -> 6.324 | R8: =(L8+J8)/2 -> 4.325 | S8: =(M8+K8)/2 -> 0.55 | T8: =('Investor-Inputs'!$G$19 * Q8) + ('Investor-Inputs'!$J$19 * R8) + ('Investor-Inputs'!$N$19 * S8) -> 28.172 | U8: =_xlfn.RANK.EQ(T8,$T$7:$T$592,0) -> 554
C9: Aditya Birla Sun Life Nifty Next 50 Index Fund - Regular Plan | D9: 4 | E9: Unlock | F9: Equity: Large Cap | G9: 8.12 | H9: 6.8 | I9: 20.35 | J9: 10.29 | M9: 0.89 | N9: Very High | O9: Above Avg. | P9: Direct | Q9: =I9*0.4+K9*0.5 -> 8.14 | R9: =(L9+J9)/2 -> 5.145 | S9: =(M9+K9)/2 -> 0.445 | T9: =('Investor-Inputs'!$G$19 * Q9) + ('Investor-Inputs'!$J$19 * R9) + ('Investor-Inputs'!$N$19 * S9) -> 35.155 | U9: =_xlfn.RANK.EQ(T9,$T$7:$T$592,0) -> 389
C10: Bandhan Large Cap Fund - Regular Plan | D10: 4 | E10: Unlock | F10: Equity: Large Cap | G10: 2.79 | H10: -2.89 | I10: 14.78 | J10: 7.14 | K10: 12.89 | L10: 10.4 | M10: 2.24 | N10: Very High | O10: Above Avg. | P10: Direct | Q10: =I10*0.4+K10*0.5 -> 12.357 | R10: =(L10+J10)/2 -> 8.77 | S10: =(M10+K10)/2 -> 7.565 | T10: =('Investor-Inputs'!$G$19 * Q10) + ('Investor-Inputs'!$J$19 * R10) + ('Investor-Inputs'!$N$19 * S10) -> 62.176 | U10: =_xlfn.RANK.EQ(T10,$T$7:$T$592,0) -> 226
C11: Baroda BNP Paribas Large Cap Fund - Regular Plan | D11: 4 | E11: Unlock | F11: Equity: Large Cap | G11: 2.57 | H11: -0.27 | I11: 14.44 | J11: 6.72 | K11: 13.07 | L11: 10.53 | M11: 2 | N11: Very High | O11: Above Avg. | P11: Direct | Q11: =I11*0.4+K11*0.5 -> 12.311 | R11: =(L11+J11)/2 -> 8.625 | S11: =(M11+K11)/2 -> 7.535 | T11: =('Investor-Inputs'!$G$19 * Q11) + ('Investor-Inputs'!$J$19 * R11) + ('Investor-Inputs'!$N$19 * S11) -> 61.718 | U11: =_xlfn.RANK.EQ(T11,$T$7:$T$592,0) -> 230
C12: Canara Robeco Large Cap Fund - Regular Plan | D12: 4 | E12: Unlock | F12: Equity: Large Cap | G12: -1.43 | H12: -6.93 | I12: 12.6 | J12: 4.99 | K12: 11.37 | L12: 8.71 | M12: 1.75 | N12: Very High | O12: Avg. | P12: Direct | Q12: =I12*0.4+K12*0.5 -> 10.725 | R12: =(L12+J12)/2 -> 6.85 | S12: =(M12+K12)/2 -> 6.56 | T12: =('Investor-Inputs'!$G$19 * Q12) + ('Investor-Inputs'!$J$19 * R12) + ('Investor-Inputs'!$N$19 * S12) -> 52.435 | U12: =_xlfn.RANK.EQ(T12,$T$7:$T$592,0) -> 275
C13: DSP Large Cap Fund - Regular Plan | D13: 5 | E13: Unlock | F13: Equity: Large Cap | G13: -2.41 | H13: -6.84 | I13: 15.09 | J13: 6.23 | K13: 12.28 | L13: 10.35 | M13: 2.52 | N13: Very High | O13: Above Avg. | P13: Direct | Q13: =I13*0.4+K13*0.5 -> 12.176 | R13: =(L13+J13)/2 -> 8.29 | S13: =(M13+K13)/2 -> 7.4 | T13: =('Investor-Inputs'!$G$19 * Q13) + ('Investor-Inputs'!$J$19 * R13) + ('Investor-Inputs'!$N$19 * S13) -> 60.508 | U13: =_xlfn.RANK.EQ(T13,$T$7:$T$592,0) -> 236
C14: DSP Nifty 50 Equal Weight Index Fund - Regular Plan | D14: 5 | E14: Unlock | F14: Equity: Large Cap | G14: 6.81 | H14: 2.67 | I14: 15.95 | J14: 8.77 | K14: 14.83 | L14: 12.24 | M14: 0.95 | N14: Very High | O14: Above Avg. | P14: Direct | Q14: =I14*0.4+K14*0.5 -> 13.795 | R14: =(L14+J14)/2 -> 10.505 | S14: =(M14+K14)/2 -> 7.89 | T14: =('Investor-Inputs'!$G$19 * Q14) + ('Investor-Inputs'!$J$19 * R14) + ('Investor-Inputs'!$N$19 * S14) -> 70.285 | U14: =_xlfn.RANK.EQ(T14,$T$7:$T$592,0) -> 192
C15: DSP Nifty Next 50 Index Fund - Regular Plan | D15: 4 | E15: Unlock | F15: Equity: Large Cap | G15: 8.35 | H15: 6.86 | I15: 20.83 | J15: 10.65 | K15: 15.1 | L15: 13.33 | M15: 0.98 | N15: Very High | O15: High | P15: Direct | Q15: =I15*0.4+K15*0.5 -> 15.882 | R15: =(L15+J15)/2 -> 11.99 | S15: =(M15+K15)/2 -> 8.04 | T15: =('Investor-Inputs'!$G$19 * Q15) + ('Investor-Inputs'!$J$19 * R15) + ('Investor-Inputs'!$N$19 * S15) -> 79.666 | U15: =_xlfn.RANK.EQ(T15,$T$7:$T$592,0) -> 132
C16: Edelweiss Large Cap Fund - Regular Plan | D16: 4 | E16: Unlock | F16: Equity: Large Cap | G16: -0.09 | H16: -5.13 | I16: 12.29 | J16: 4.59 | K16: 12.11 | L16: 9 | M16: 2.12 | N16: Very High | O16: Avg. | P16: Direct | Q16: =I16*0.4+K16*0.5 -> 10.971 | R16: =(L16+J16)/2 -> 6.795 | S16: =(M16+K16)/2 -> 7.115 | T16: =('Investor-Inputs'!$G$19 * Q16) + ('Investor-Inputs'!$J$19 * R16) + ('Investor-Inputs'!$N$19 * S16) -> 53.618 | U16: =_xlfn.RANK.EQ(T16,$T$7:$T$592,0) -> 273
C17: HDFC Large Cap Fund - Regular Plan | D17: 5 | E17: Unlock | F17: Equity: Large Cap | G17: -1.59 | H17: -6.6 | I17: 12.48 | J17: 3.95 | K17: 13.84 | L17: 9.59 | M17: 1.58 | N17: Very High | O17: Above Avg. | P17: Direct | Q17: =I17*0.4+K17*0.5 -> 11.912 | R17: =(L17+J17)/2 -> 6.77 | S17: =(M17+K17)/2 -> 7.71 | T17: =('Investor-Inputs'!$G$19 * Q17) + ('Investor-Inputs'!$J$19 * R17) + ('Investor-Inputs'!$N$19 * S17) -> 56.986 | U17: =_xlfn.RANK.EQ(T17,$T$7:$T$592,0) -> 246
C18: HDFC NIFTY 100 Equal Weight Index Fund - Regular Plan | D18: 4 | E18: Unlock | F18: Equity: Large Cap | G18: 7.88 | H18: 4.9 | I18: 18.08 | J18: 9.68 | M18: 0.88 | N18: Very High | O18: Above Avg. | P18: Direct | Q18: =I18*0.4+K18*0.5 -> 7.232 | R18: =(L18+J18)/2 -> 4.84 | S18: =(M18+K18)/2 -> 0.44 | T18: =('Investor-Inputs'!$G$19 * Q18) + ('Investor-Inputs'!$J$19 * R18) + ('Investor-Inputs'!$N$19 * S18) -> 31.816 | U18: =_xlfn.RANK.EQ(T18,$T$7:$T$592,0) -> 504
C19: HDFC NIFTY50 Equal Weight Index Fund - Regular Plan | D19: 5 | E19: Unlock | F19: Equity: Large Cap | G19: 6.85 | H19: 2.71 | I19: 16.02 | J19: 8.85 | M19: 1 | N19: Very High | O19: Above Avg. | P19: Direct | Q19: =I19*0.4+K19*0.5 -> 6.408 | R19: =(L19+J19)/2 -> 4.425 | S19: =(M19+K19)/2 -> 0.5 | T19: =('Investor-Inputs'!$G$19 * Q19) + ('Investor-Inputs'!$J$19 * R19) + ('Investor-Inputs'!$N$19 * S19) -> 28.574 | U19: =_xlfn.RANK.EQ(T19,$T$7:$T$592,0) -> 546
C20: ICICI Prudential BHARAT 22 FOF | D20: 5 | E20: Unlock | F20: Equity: Large Cap | G20: 17.4 | H20: 18.98 | I20: 25.53 | J20: 16.37 | K20: 28 | L20: 23.73 | M20: 0.14 | N20: Very High | O20: High | P20: Direct | Q20: =I20*0.4+K20*0.5 -> 24.212 | R20: =(L20+J20)/2 -> 20.05 | S20: =(M20+K20)/2 -> 14.07 | T20: =('Investor-Inputs'!$G$19 * Q20) + ('Investor-Inputs'!$J$19 * R20) + ('Investor-Inputs'!$N$19 * S20) -> 126.806 | U20: =_xlfn.RANK.EQ(T20,$T$7:$T$592,0) -> 7
C21: ICICI Prudential Large Cap Fund | D21: 5 | E21: Unlock | F21: Equity: Large Cap | G21: 0.07 | H21: -5.94 | I21: 15.26 | J21: 6.51 | K21: 14.67 | L21: 11.25 | M21: 3.59 | N21: Very High | O21: Above Avg. | P21: Direct | Q21: =I21*0.4+K21*0.5 -> 13.439 | R21: =(L21+J21)/2 -> 8.88 | S21: =(M21+K21)/2 -> 9.13 | T21: =('Investor-Inputs'!$G$19 * Q21) + ('Investor-Inputs'!$J$19 * R21) + ('Investor-Inputs'!$N$19 * S21) -> 67.207 | U21: =_xlfn.RANK.EQ(T21,$T$7:$T$592,0) -> 202
C22: ICICI Prudential Nifty 100 Low Volatility 30 ETF FOF | D22: 4 | E22: Unlock | F22: Equity: Large Cap | G22: 1.08 | H22: -4.13 | I22: 13.56 | J22: 5.49 | K22: 12.11 | L22: 9.43 | M22: 0.58 | N22: Very High | O22: Avg. | P22: Direct | Q22: =I22*0.4+K22*0.5 -> 11.479 | R22: =(L22+J22)/2 -> 7.46 | S22: =(M22+K22)/2 -> 6.345 | T22: =('Investor-Inputs'!$G$19 * Q22) + ('Investor-Inputs'!$J$19 * R22) + ('Investor-Inputs'!$N$19 * S22) -> 55.702 | U22: =_xlfn.RANK.EQ(T22,$T$7:$T$592,0) -> 258
C23: ICICI Prudential Nifty50 Equal Weight Index Fund | D23: 4 | E23: Unlock | F23: Equity: Large Cap | G23: 6.65 | H23: 2.53 | I23: 15.8 | J23: 8.67 | M23: 1.25 | N23: Very High | O23: Above Avg. | P23: Direct | Q23: =I23*0.4+K23*0.5 -> 6.32 | R23: =(L23+J23)/2 -> 4.335 | S23: =(M23+K23)/2 -> 0.625 | T23: =('Investor-Inputs'!$G$19 * Q23) + ('Investor-Inputs'!$J$19 * R23) + ('Investor-Inputs'!$N$19 * S23) -> 28.255 | U23: =_xlfn.RANK.EQ(T23,$T$7:$T$592,0) -> 552
C24: Invesco India Largecap Fund - Regular Plan | D24: 4 | E24: Unlock | F24: Equity: Large Cap | G24: 2.12 | H24: -3.12 | I24: 15.53 | J24: 7 | K24: 13.55 | L24: 10.5 | M24: 2.08 | N24: Very High | O24: Above Avg. | P24: Direct | Q24: =I24*0.4+K24*0.5 -> 12.987 | R24: =(L24+J24)/2 -> 8.75 | S24: =(M24+K24)/2 -> 7.815 | T24: =('Investor-Inputs'!$G$19 * Q24) + ('Investor-Inputs'!$J$19 * R24) + ('Investor-Inputs'!$N$19 * S24) -> 64.276 | U24: =_xlfn.RANK.EQ(T24,$T$7:$T$592,0) -> 212
C25: Kotak Large Cap Fund - Regular Plan | D25: 4 | E25: Unlock | F25: Equity: Large Cap | G25: 0.86 | H25: -5.19 | I25: 12.92 | J25: 5.64 | K25: 12.12 | L25: 9.24 | M25: 1.89 | N25: Very High | O25: Avg. | P25: Direct | Q25: =I25*0.4+K25*0.5 -> 11.228 | R25: =(L25+J25)/2 -> 7.44 | S25: =(M25+K25)/2 -> 7.005 | T25: =('Investor-Inputs'!$G$19 * Q25) + ('Investor-Inputs'!$J$19 * R25) + ('Investor-Inputs'!$N$19 * S25) -> 55.569 | U25: =_xlfn.RANK.EQ(T25,$T$7:$T$592,0) -> 262
C26: Kotak Nifty Next 50 Index Fund - Regular Plan | D26: 4 | E26: Unlock | F26: Equity: Large Cap | G26: 8.33 | H26: 6.98 | I26: 20.72 | J26: 10.66 | K26: 15.03 | L26: 13.29 | M26: 0.9 | N26: Very High | O26: High | P26: Direct | Q26: =I26*0.4+K26*0.5 -> 15.803 | R26: =(L26+J26)/2 -> 11.975 | S26: =(M26+K26)/2 -> 7.965 | T26: =('Investor-Inputs'!$G$19 * Q26) + ('Investor-Inputs'!$J$19 * R26) + ('Investor-Inputs'!$N$19 * S26) -> 79.324 | U26: =_xlfn.RANK.EQ(T26,$T$7:$T$592,0) -> 134
C27: Mirae Asset Diversified Equity Allocator Passive FoF - Regular Plan | D27: 4 | E27: Unlock | F27: Equity: Large Cap | G27: 3.38 | H27: -1.33 | I27: 14.48 | J27: 6.77 | K27: 13.29 | L27: 10.45 | M27: 0.11 | N27: Very High | O27: Above Avg. | P27: Direct | Q27: =I27*0.4+K27*0.5 -> 12.437 | R27: =(L27+J27)/2 -> 8.61 | S27: =(M27+K27)/2 -> 6.7 | T27: =('Investor-Inputs'!$G$19 * Q27) + ('Investor-Inputs'!$J$19 * R27) + ('Investor-Inputs'!$N$19 * S27) -> 61.231 | U27: =_xlfn.RANK.EQ(T27,$T$7:$T$592,0) -> 232
C28: Navi Nifty Next 50 Index Fund - Regular Plan | D28: 4 | E28: Unlock | F28: Equity: Large Cap | G28: 7.86 | H28: 6.38 | I28: 20.48 | J28: 10.34 | M28: 1.07 | N28: Very High | O28: Above Avg. | P28: Direct | Q28: =I28*0.4+K28*0.5 -> 8.192 | R28: =(L28+J28)/2 -> 5.17 | S28: =(M28+K28)/2 -> 0.535 | T28: =('Investor-Inputs'!$G$19 * Q28) + ('Investor-Inputs'!$J$19 * R28) + ('Investor-Inputs'!$N$19 * S28) -> 35.451 | U28: =_xlfn.RANK.EQ(T28,$T$7:$T$592,0) -> 383
C29: Nippon India Large Cap Fund | D29: 5 | E29: Unlock | F29: Equity: Large Cap | G29: 3.05 | H29: -3.29 | I29: 16.16 | J29: 7.34 | K29: 17.08 | L29: 12.88 | M29: 2.08 | N29: Very High | O29: Above Avg. | P29: Direct | Q29: =I29*0.4+K29*0.5 -> 15.004 | R29: =(L29+J29)/2 -> 10.11 | S29: =(M29+K29)/2 -> 9.58 | T29: =('Investor-Inputs'!$G$19 * Q29) + ('Investor-Inputs'!$J$19 * R29) + ('Investor-Inputs'!$N$19 * S29) -> 74.812 | U29: =_xlfn.RANK.EQ(T29,$T$7:$T$592,0) -> 162
C30: Nippon India Nifty Next 50 Junior BeES FoF - Regular Plan | D30: 4 | E30: Unlock | F30: Equity: Large Cap | G30: 9.02 | H30: 7.57 | I30: 21.18 | J30: 11.12 | K30: 15.23 | L30: 13.65 | M30: 0.3 | N30: Very High | O30: High | P30: Direct | Q30: =I30*0.4+K30*0.5 -> 16.087 | R30: =(L30+J30)/2 -> 12.385 | S30: =(M30+K30)/2 -> 7.765 | T30: =('Investor-Inputs'!$G$19 * Q30) + ('Investor-Inputs'!$J$19 * R30) + ('Investor-Inputs'!$N$19 * S30) -> 80.796 | U30: =_xlfn.RANK.EQ(T30,$T$7:$T$592,0) -> 130
C31: SBI Large Cap Fund | D31: 4 | E31: Unlock | F31: Equity: Large Cap | G31: 2.32 | H31: -2.17 | I31: 12.03 | J31: 6.1 | K31: 12.24 | L31: 9.46 | M31: 1.47 | N31: Very High | O31: Avg. | P31: Direct | Q31: =I31*0.4+K31*0.5 -> 10.932 | R31: =(L31+J31)/2 -> 7.78 | S31: =(M31+K31)/2 -> 6.855 | T31: =('Investor-Inputs'!$G$19 * Q31) + ('Investor-Inputs'!$J$19 * R31) + ('Investor-Inputs'!$N$19 * S31) -> 55.211 | U31: =_xlfn.RANK.EQ(T31,$T$7:$T$592,0) -> 268
C32: SBI Nifty Next 50 Index Fund - Regular Plan | D32: 5 | E32: Unlock | F32: Equity: Large Cap | G32: 8.24 | H32: 6.83 | I32: 20.71 | J32: 10.59 | M32: 0.71 | N32: Very High | O32: High | P32: Direct | Q32: =I32*0.4+K32*0.5 -> 8.284 | R32: =(L32+J32)/2 -> 5.295 | S32: =(M32+K32)/2 -> 0.355 | T32: =('Investor-Inputs'!$G$19 * Q32) + ('Investor-Inputs'!$J$19 * R32) + ('Investor-Inputs'!$N$19 * S32) -> 35.797 | U32: =_xlfn.RANK.EQ(T32,$T$7:$T$592,0) -> 359
C33: Sundaram Nifty 100 Equal Weight Fund | D33: 4 | E33: Unlock | F33: Equity: Large Cap | G33: 7.83 | H33: 5.02 | I33: 17.79 | J33: 9.55 | K33: 14.25 | L33: 12.35 | M33: 1.06 | N33: Very High | O33: Above Avg. | P33: Direct | Q33: =I33*0.4+K33*0.5 -> 14.241 | R33: =(L33+J33)/2 -> 10.95 | S33: =(M33+K33)/2 -> 7.655 | T33: =('Investor-Inputs'!$G$19 * Q33) + ('Investor-Inputs'!$J$19 * R33) + ('Investor-Inputs'!$N$19 * S33) -> 72.278 | U33: =_xlfn.RANK.EQ(T33,$T$7:$T$592,0) -> 182
C34: Tata Large Cap Fund - Regular Plan | D34: 4 | E34: Unlock | F34: Equity: Large Cap | G34: 2.52 | H34: -1.62 | I34: 13.25 | J34: 6.04 | K34: 12.53 | L34: 9.59 | M34: 2.33 | N34: Very High | O34: Above Avg. | P34: Direct | Q34: =I34*0.4+K34*0.5 -> 11.565 | R34: =(L34+J34)/2 -> 7.815 | S34: =(M34+K34)/2 -> 7.43 | T34: =('Investor-Inputs'!$G$19 * Q34) + ('Investor-Inputs'!$J$19 * R34) + ('Investor-Inputs'!$N$19 * S34) -> 57.755 | U34: =_xlfn.RANK.EQ(T34,$T$7:$T$592,0) -> 244
C35: WhiteOak Capital Large Cap Fund - Regular Plan | D35: 4 | E35: Unlock | F35: Equity: Large Cap | G35: 1.28 | H35: -4.43 | I35: 15.01 | J35: 7.07 | M35: 2.63 | N35: Very High | O35: Above Avg. | P35: Direct | Q35: =I35*0.4+K35*0.5 -> 6.004 | R35: =(L35+J35)/2 -> 3.535 | S35: =(M35+K35)/2 -> 1.315 | T35: =('Investor-Inputs'!$G$19 * Q35) + ('Investor-Inputs'!$J$19 * R35) + ('Investor-Inputs'!$N$19 * S35) -> 26.397 | U35: =_xlfn.RANK.EQ(T35,$T$7:$T$592,0) -> 566
C36: Bandhan Large & Mid Cap Fund - Regular Plan | D36: 5 | E36: Unlock | F36: Equity: Large & MidCap | G36: 9.77 | H36: 5.76 | I36: 23.13 | J36: 13.09 | K36: 19.12 | L36: 17.22 | M36: 2.9 | N36: Very High | O36: High | P36: Direct | Q36: =I36*0.4+K36*0.5 -> 18.812 | R36: =(L36+J36)/2 -> 15.155 | S36: =(M36+K36)/2 -> 11.01 | T36: =('Investor-Inputs'!$G$19 * Q36) + ('Investor-Inputs'!$J$19 * R36) + ('Investor-Inputs'!$N$19 * S36) -> 97.756 | U36: =_xlfn.RANK.EQ(T36,$T$7:$T$592,0) -> 53
C37: DSP Large & Mid Cap Fund - Regular Plan | D37: 4 | E37: Unlock | F37: Equity: Large & MidCap | G37: 1.71 | H37: -3 | I37: 18.4 | J37: 8.3 | K37: 15.02 | L37: 12.74 | M37: 2.12 | N37: Very High | O37: Above Avg. | P37: Direct | Q37: =I37*0.4+K37*0.5 -> 14.87 | R37: =(L37+J37)/2 -> 10.52 | S37: =(M37+K37)/2 -> 8.57 | T37: =('Investor-Inputs'!$G$19 * Q37) + ('Investor-Inputs'!$J$19 * R37) + ('Investor-Inputs'!$N$19 * S37) -> 74.22 | U37: =_xlfn.RANK.EQ(T37,$T$7:$T$592,0) -> 166
C38: HDFC Large and Mid Cap Fund - Regular Plan | D38: 4 | E38: Unlock | F38: Equity: Large & MidCap | G38: 3.83 | H38: -2.27 | I38: 17.9 | J38: 7.49 | K38: 17.56 | L38: 13.3 | M38: 1.59 | N38: Very High | O38: Above Avg. | P38: Direct | Q38: =I38*0.4+K38*0.5 -> 15.94 | R38: =(L38+J38)/2 -> 10.395 | S38: =(M38+K38)/2 -> 9.575 | T38: =('Investor-Inputs'!$G$19 * Q38) + ('Investor-Inputs'!$J$19 * R38) + ('Investor-Inputs'!$N$19 * S38) -> 78.185 | U38: =_xlfn.RANK.EQ(T38,$T$7:$T$592,0) -> 142
C39: ICICI Prudential Large & Mid Cap Fund | D39: 5 | E39: Unlock | F39: Equity: Large & MidCap | G39: 4.76 | H39: -0.1 | I39: 19.51 | J39: 10.55 | K39: 19.35 | L39: 15.25 | M39: 2.32 | N39: Very High | O39: Above Avg. | P39: Direct | Q39: =I39*0.4+K39*0.5 -> 17.479 | R39: =(L39+J39)/2 -> 12.9 | S39: =(M39+K39)/2 -> 10.835 | T39: =('Investor-Inputs'!$G$19 * Q39) + ('Investor-Inputs'!$J$19 * R39) + ('Investor-Inputs'!$N$19 * S39) -> 89.072 | U39: =_xlfn.RANK.EQ(T39,$T$7:$T$592,0) -> 83
C40: Invesco India Large & Mid Cap Fund - Regular Plan | D40: 4 | E40: Unlock | F40: Equity: Large & MidCap | G40: 8.69 | H40: 0.98 | I40: 23.14 | J40: 13.51 | K40: 17.71 | L40: 16.59 | M40: 1.9 | N40: Very High | O40: High | P40: Direct | Q40: =I40*0.4+K40*0.5 -> 18.111 | R40: =(L40+J40)/2 -> 15.05 | S40: =(M40+K40)/2 -> 9.805 | T40: =('Investor-Inputs'!$G$19 * Q40) + ('Investor-Inputs'!$J$19 * R40) + ('Investor-Inputs'!$N$19 * S40) -> 94.238 | U40: =_xlfn.RANK.EQ(T40,$T$7:$T$592,0) -> 61
C41: Motilal Oswal Large and Midcap Fund - Regular Plan | D41: 4 | E41: Unlock | F41: Equity: Large & MidCap | G41: 15.63 | H41: 9.31 | I41: 25.52 | J41: 15.88 | K41: 20.97 | L41: 19.38 | M41: 1.91 | N41: Very High | O41: High | P41: Direct | Q41: =I41*0.4+K41*0.5 -> 20.693 | R41: =(L41+J41)/2 -> 17.63 | S41: =(M41+K41)/2 -> 11.44 | T41: =('Investor-Inputs'!$G$19 * Q41) + ('Investor-Inputs'!$J$19 * R41) + ('Investor-Inputs'!$N$19 * S41) -> 108.779 | U41: =_xlfn.RANK.EQ(T41,$T$7:$T$592,0) -> 35
C42: Nippon India Vision Large & Mid Cap Fund | D42: 4 | E42: Unlock | F42: Equity: Large & MidCap | G42: 3.77 | H42: -0.43 | I42: 19.32 | J42: 9.72 | K42: 16.65 | L42: 13.98 | M42: 1.8 | N42: Very High | O42: Above Avg. | P42: Direct | Q42: =I42*0.4+K42*0.5 -> 16.053 | R42: =(L42+J42)/2 -> 11.85 | S42: =(M42+K42)/2 -> 9.225 | T42: =('Investor-Inputs'!$G$19 * Q42) + ('Investor-Inputs'!$J$19 * R42) + ('Investor-Inputs'!$N$19 * S42) -> 81.084 | U42: =_xlfn.RANK.EQ(T42,$T$7:$T$592,0) -> 124
C43: SBI Large & Midcap Fund | D43: 4 | E43: Unlock | F43: Equity: Large & MidCap | G43: 7.36 | H43: 1 | I43: 16.09 | J43: 9.1 | K43: 16.53 | L43: 12.82 | M43: 1.72 | N43: Very High | O43: Avg. | P43: Direct | Q43: =I43*0.4+K43*0.5 -> 14.701 | R43: =(L43+J43)/2 -> 10.96 | S43: =(M43+K43)/2 -> 9.125 | T43: =('Investor-Inputs'!$G$19 * Q43) + ('Investor-Inputs'!$J$19 * R43) + ('Investor-Inputs'!$N$19 * S43) -> 75.148 | U43: =_xlfn.RANK.EQ(T43,$T$7:$T$592,0) -> 156
C44: UTI Large & Mid Cap Fund - Regular Plan | D44: 5 | E44: Unlock | F44: Equity: Large & MidCap | G44: 6.37 | H44: 2.1 | I44: 20.12 | J44: 10.84 | K44: 17.61 | L44: 15.01 | M44: 1.85 | N44: Very High | O44: Above Avg. | P44: Direct | Q44: =I44*0.4+K44*0.5 -> 16.853 | R44: =(L44+J44)/2 -> 12.925 | S44: =(M44+K44)/2 -> 9.73 | T44: =('Investor-Inputs'!$G$19 * Q44) + ('Investor-Inputs'!$J$19 * R44) + ('Investor-Inputs'!$N$19 * S44) -> 86.139 | U44: =_xlfn.RANK.EQ(T44,$T$7:$T$592,0) -> 106
C45: Aditya Birla Sun Life Flexi Cap Fund - Regular Plan | D45: 4 | E45: Unlock | F45: Equity: Flexi Cap | G45: 6.66 | H45: 2.86 | I45: 17.36 | J45: 10.21 | K45: 13.7 | L45: 12.34 | M45: 1.6 | N45: Very High | O45: Above Avg. | P45: Direct | Q45: =I45*0.4+K45*0.5 -> 13.794 | R45: =(L45+J45)/2 -> 11.275 | S45: =(M45+K45)/2 -> 7.65 | T45: =('Investor-Inputs'!$G$19 * Q45) + ('Investor-Inputs'!$J$19 * R45) + ('Investor-Inputs'!$N$19 * S45) -> 71.582 | U45: =_xlfn.RANK.EQ(T45,$T$7:$T$592,0) -> 186
C46: Bank of India Flexi Cap Fund - Regular Plan | D46: 4 | E46: Unlock | F46: Equity: Flexi Cap | G46: 14.82 | H46: 11.25 | I46: 21.8 | J46: 12.44 | K46: 18.51 | L46: 16.03 | M46: 2.96 | N46: Very High | O46: High | P46: Direct | Q46: =I46*0.4+K46*0.5 -> 17.975 | R46: =(L46+J46)/2 -> 14.235 | S46: =(M46+K46)/2 -> 10.735 | T46: =('Investor-Inputs'!$G$19 * Q46) + ('Investor-Inputs'!$J$19 * R46) + ('Investor-Inputs'!$N$19 * S46) -> 93.13 | U46: =_xlfn.RANK.EQ(T46,$T$7:$T$592,0) -> 71
C47: Canara Robeco Focused Fund - Regular Plan | D47: 4 | E47: Unlock | F47: Equity: Flexi Cap | G47: 1.98 | H47: -6.64 | I47: 14.93 | J47: 6.59 | M47: 2.09 | N47: Very High | O47: Avg. | P47: Direct | Q47: =I47*0.4+K47*0.5 -> 5.972 | R47: =(L47+J47)/2 -> 3.295 | S47: =(M47+K47)/2 -> 1.045 | T47: =('Investor-Inputs'!$G$19 * Q47) + ('Investor-Inputs'!$J$19 * R47) + ('Investor-Inputs'!$N$19 * S47) -> 25.551 | U47: =_xlfn.RANK.EQ(T47,$T$7:$T$592,0) -> 568
C48: Edelweiss Flexi Cap Fund - Regular Plan | D48: 4 | E48: Unlock | F48: Equity: Flexi Cap | G48: 4.73 | H48: -0.41 | I48: 17.16 | J48: 8.55 | K48: 15.17 | L48: 12.36 | M48: 1.92 | N48: Very High | O48: Above Avg. | P48: Direct | Q48: =I48*0.4+K48*0.5 -> 14.449 | R48: =(L48+J48)/2 -> 10.455 | S48: =(M48+K48)/2 -> 8.545 | T48: =('Investor-Inputs'!$G$19 * Q48) + ('Investor-Inputs'!$J$19 * R48) + ('Investor-Inputs'!$N$19 * S48) -> 72.802 | U48: =_xlfn.RANK.EQ(T48,$T$7:$T$592,0) -> 178
C49: Edelweiss Focused Fund - Regular Plan | D49: 4 | E49: Unlock | F49: Equity: Flexi Cap | G49: 2.37 | H49: -2.24 | I49: 15.37 | J49: 6.9 | M49: 2.23 | N49: Very High | O49: Above Avg. | P49: Direct | Q49: =I49*0.4+K49*0.5 -> 6.148 | R49: =(L49+J49)/2 -> 3.45 | S49: =(M49+K49)/2 -> 1.115 | T49: =('Investor-Inputs'!$G$19 * Q49) + ('Investor-Inputs'!$J$19 * R49) + ('Investor-Inputs'!$N$19 * S49) -> 26.459 | U49: =_xlfn.RANK.EQ(T49,$T$7:$T$592,0) -> 564
C50: Franklin India Flexi Cap Fund - Regular Plan | D50: 4 | E50: Unlock | F50: Equity: Flexi Cap | G50: -1.39 | H50: -6.27 | I50: 16 | J50: 5.83 | K50: 15.39 | L50: 11.21 | M50: 1.71 | N50: Very High | O50: Above Avg. | P50: Direct | Q50: =I50*0.4+K50*0.5 -> 14.095 | R50: =(L50+J50)/2 -> 8.52 | S50: =(M50+K50)/2 -> 8.55 | T50: =('Investor-Inputs'!$G$19 * Q50) + ('Investor-Inputs'!$J$19 * R50) + ('Investor-Inputs'!$N$19 * S50) -> 67.875 | U50: =_xlfn.RANK.EQ(T50,$T$7:$T$592,0) -> 198
C51: Franklin India Focused Equity Fund - Regular Plan | D51: 4 | E51: Unlock | F51: Equity: Flexi Cap | G51: -2.84 | H51: -9.87 | I51: 13.16 | J51: 3.34 | K51: 13.83 | L51: 8.99 | M51: 1.88 | N51: Very High | O51: Avg. | P51: Direct | Q51: =I51*0.4+K51*0.5 -> 12.179 | R51: =(L51+J51)/2 -> 6.165 | S51: =(M51+K51)/2 -> 7.855 | T51: =('Investor-Inputs'!$G$19 * Q51) + ('Investor-Inputs'!$J$19 * R51) + ('Investor-Inputs'!$N$19 * S51) -> 56.722 | U51: =_xlfn.RANK.EQ(T51,$T$7:$T$592,0) -> 250
C52: HDFC Flexi Cap Fund - Regular Plan | D52: 5 | E52: Unlock | F52: Equity: Flexi Cap | G52: 1.23 | H52: -4.64 | I52: 18.76 | J52: 9.62 | K52: 19.54 | L52: 15.3 | M52: 1.27 | N52: Very High | O52: High | P52: Direct | Q52: =I52*0.4+K52*0.5 -> 17.274 | R52: =(L52+J52)/2 -> 12.46 | S52: =(M52+K52)/2 -> 10.405 | T52: =('Investor-Inputs'!$G$19 * Q52) + ('Investor-Inputs'!$J$19 * R52) + ('Investor-Inputs'!$N$19 * S52) -> 87.147 | U52: =_xlfn.RANK.EQ(T52,$T$7:$T$592,0) -> 93
C53: HDFC Focused Fund - Regular Plan | D53: 5 | E53: Unlock | F53: Equity: Flexi Cap | G53: 0.44 | H53: -6.25 | I53: 17.86 | J53: 8.88 | K53: 20.23 | L53: 15.12 | M53: 1.6 | N53: Very High | O53: High | P53: Direct | Q53: =I53*0.4+K53*0.5 -> 17.259 | R53: =(L53+J53)/2 -> 12 | S53: =(M53+K53)/2 -> 10.915 | T53: =('Investor-Inputs'!$G$19 * Q53) + ('Investor-Inputs'!$J$19 * R53) + ('Investor-Inputs'!$N$19 * S53) -> 86.692 | U53: =_xlfn.RANK.EQ(T53,$T$7:$T$592,0) -> 96
C54: HDFC Retirement Savings Fund - Equity Plan - Regular Plan | D54: 4 | E54: Unlock | F54: Equity: Flexi Cap | G54: -1.51 | H54: -7.69 | I54: 13.6 | J54: 4.23 | K54: 15.97 | L54: 10.71 | M54: 1.83 | N54: Very High | O54: Avg. | P54: Direct | Q54: =I54*0.4+K54*0.5 -> 13.425 | R54: =(L54+J54)/2 -> 7.47 | S54: =(M54+K54)/2 -> 8.9 | T54: =('Investor-Inputs'!$G$19 * Q54) + ('Investor-Inputs'!$J$19 * R54) + ('Investor-Inputs'!$N$19 * S54) -> 64.115 | U54: =_xlfn.RANK.EQ(T54,$T$7:$T$592,0) -> 214
C55: HSBC Flexi Cap Fund | D55: 4 | E55: Unlock | F55: Equity: Flexi Cap | G55: 8.05 | H55: 3.56 | I55: 18.27 | J55: 9.97 | K55: 15.49 | L55: 13.23 | M55: 2.3 | N55: Very High | O55: Above Avg. | P55: Direct | Q55: =I55*0.4+K55*0.5 -> 15.053 | R55: =(L55+J55)/2 -> 11.6 | S55: =(M55+K55)/2 -> 8.895 | T55: =('Investor-Inputs'!$G$19 * Q55) + ('Investor-Inputs'!$J$19 * R55) + ('Investor-Inputs'!$N$19 * S55) -> 77.254 | U55: =_xlfn.RANK.EQ(T55,$T$7:$T$592,0) -> 148
C56: ICICI Prudential Diversified Equity All Cap Omni FoF | D56: 5 | E56: Unlock | F56: Equity: Flexi Cap | G56: 2.85 | H56: -0.6 | I56: 18.97 | J56: 9.7 | K56: 17.79 | L56: 14.33 | M56: 0.98 | N56: Very High | O56: High | P56: Direct | Q56: =I56*0.4+K56*0.5 -> 16.483 | R56: =(L56+J56)/2 -> 12.015 | S56: =(M56+K56)/2 -> 9.385 | T56: =('Investor-Inputs'!$G$19 * Q56) + ('Investor-Inputs'!$J$19 * R56) + ('Investor-Inputs'!$N$19 * S56) -> 82.864 | U56: =_xlfn.RANK.EQ(T56,$T$7:$T$592,0) -> 118
C57: ICICI Prudential Flexicap Fund | D57: 4 | E57: Unlock | F57: Equity: Flexi Cap | G57: 7.85 | H57: 0.06 | I57: 17.49 | J57: 9.1 | M57: 1.77 | N57: Very High | O57: Above Avg. | P57: Direct | Q57: =I57*0.4+K57*0.5 -> 6.996 | R57: =(L57+J57)/2 -> 4.55 | S57: =(M57+K57)/2 -> 0.885 | T57: =('Investor-Inputs'!$G$19 * Q57) + ('Investor-Inputs'!$J$19 * R57) + ('Investor-Inputs'!$N$19 * S57) -> 30.973 | U57: =_xlfn.RANK.EQ(T57,$T$7:$T$592,0) -> 510
C58: ICICI Prudential Focused Equity Fund | D58: 5 | E58: Unlock | F58: Equity: Flexi Cap | G58: 3.28 | H58: -3.63 | I58: 19.91 | J58: 10.72 | K58: 17.9 | L58: 14.94 | M58: 2.37 | N58: Very High | O58: High | P58: Direct | Q58: =I58*0.4+K58*0.5 -> 16.914 | R58: =(L58+J58)/2 -> 12.83 | S58: =(M58+K58)/2 -> 10.135 | T58: =('Investor-Inputs'!$G$19 * Q58) + ('Investor-Inputs'!$J$19 * R58) + ('Investor-Inputs'!$N$19 * S58) -> 86.537 | U58: =_xlfn.RANK.EQ(T58,$T$7:$T$592,0) -> 100
C59: ICICI Prudential Retirement Fund - Pure Equity Plan | D59: 5 | E59: Unlock | F59: Equity: Flexi Cap | G59: 16.83 | H59: 10.82 | I59: 24.99 | J59: 16.19 | K59: 22.43 | L59: 19.21 | M59: 2.09 | N59: Very High | O59: High | P59: Direct | Q59: =I59*0.4+K59*0.5 -> 21.211 | R59: =(L59+J59)/2 -> 17.7 | S59: =(M59+K59)/2 -> 12.26 | T59: =('Investor-Inputs'!$G$19 * Q59) + ('Investor-Inputs'!$J$19 * R59) + ('Investor-Inputs'!$N$19 * S59) -> 111.293 | U59: =_xlfn.RANK.EQ(T59,$T$7:$T$592,0) -> 27
C60: Invesco India Flexi Cap Fund - Regular Plan | D60: 4 | E60: Unlock | F60: Equity: Flexi Cap | G60: 1.78 | H60: -6.19 | I60: 18.68 | J60: 7.97 | M60: 1.86 | N60: Very High | O60: High | P60: Direct | Q60: =I60*0.4+K60*0.5 -> 7.472 | R60: =(L60+J60)/2 -> 3.985 | S60: =(M60+K60)/2 -> 0.93 | T60: =('Investor-Inputs'!$G$19 * Q60) + ('Investor-Inputs'!$J$19 * R60) + ('Investor-Inputs'!$N$19 * S60) -> 31.316 | U60: =_xlfn.RANK.EQ(T60,$T$7:$T$592,0) -> 508
C61: Invesco India Focused Fund - Regular Plan | D61: 4 | E61: Unlock | F61: Equity: Flexi Cap | G61: -2.85 | H61: -7.26 | I61: 21.28 | J61: 8.11 | K61: 15.82 | L61: 12.98 | M61: 1.89 | N61: Very High | O61: Above Avg. | P61: Direct | Q61: =I61*0.4+K61*0.5 -> 16.422 | R61: =(L61+J61)/2 -> 10.545 | S61: =(M61+K61)/2 -> 8.855 | T61: =('Investor-Inputs'!$G$19 * Q61) + ('Investor-Inputs'!$J$19 * R61) + ('Investor-Inputs'!$N$19 * S61) -> 79.211 | U61: =_xlfn.RANK.EQ(T61,$T$7:$T$592,0) -> 136
C62: ITI Flexi Cap Fund - Regular Plan | D62: 4 | E62: Unlock | F62: Equity: Flexi Cap | G62: 9.97 | H62: 4.39 | I62: 19.84 | J62: 10.02 | M62: 2.52 | N62: Very High | O62: High | P62: Direct | Q62: =I62*0.4+K62*0.5 -> 7.936 | R62: =(L62+J62)/2 -> 5.01 | S62: =(M62+K62)/2 -> 1.26 | T62: =('Investor-Inputs'!$G$19 * Q62) + ('Investor-Inputs'!$J$19 * R62) + ('Investor-Inputs'!$N$19 * S62) -> 35.088 | U62: =_xlfn.RANK.EQ(T62,$T$7:$T$592,0) -> 391
C63: JM Flexicap Fund | D63: 4 | E63: Unlock | F63: Equity: Flexi Cap | G63: -1.05 | H63: -4.02 | I63: 18.45 | J63: 5.13 | K63: 17.33 | L63: 12.93 | M63: 2.58 | N63: Very High | O63: Above Avg. | P63: Direct | Q63: =I63*0.4+K63*0.5 -> 16.045 | R63: =(L63+J63)/2 -> 9.03 | S63: =(M63+K63)/2 -> 9.955 | T63: =('Investor-Inputs'!$G$19 * Q63) + ('Investor-Inputs'!$J$19 * R63) + ('Investor-Inputs'!$N$19 * S63) -> 76.15 | U63: =_xlfn.RANK.EQ(T63,$T$7:$T$592,0) -> 152
C64: Kotak Focused Fund - Regular Plan | D64: 4 | E64: Unlock | F64: Equity: Flexi Cap | G64: 10 | H64: 2.92 | I64: 16.21 | J64: 9.97 | K64: 14.22 | L64: 11.98 | M64: 2.29 | N64: Very High | O64: Avg. | P64: Direct | Q64: =I64*0.4+K64*0.5 -> 13.594 | R64: =(L64+J64)/2 -> 10.975 | S64: =(M64+K64)/2 -> 8.255 | T64: =('Investor-Inputs'!$G$19 * Q64) + ('Investor-Inputs'!$J$19 * R64) + ('Investor-Inputs'!$N$19 * S64) -> 70.987 | U64: =_xlfn.RANK.EQ(T64,$T$7:$T$592,0) -> 188
C65: Mahindra Manulife Focused Fund - Regular Plan | D65: 4 | E65: Unlock | F65: Equity: Flexi Cap | G65: 3.23 | H65: 1.2 | I65: 17.74 | J65: 8.67 | K65: 16.82 | L65: 13.34 | M65: 2.13 | N65: Very High | O65: Above Avg. | P65: Direct | Q65: =I65*0.4+K65*0.5 -> 15.506 | R65: =(L65+J65)/2 -> 11.005 | S65: =(M65+K65)/2 -> 9.475 | T65: =('Investor-Inputs'!$G$19 * Q65) + ('Investor-Inputs'!$J$19 * R65) + ('Investor-Inputs'!$N$19 * S65) -> 78.003 | U65: =_xlfn.RANK.EQ(T65,$T$7:$T$592,0) -> 144
C66: Nippon India Retirement Fund - Wealth Creation Scheme | D66: 4 | E66: Unlock | F66: Equity: Flexi Cap | G66: 2.24 | H66: -1.87 | I66: 16.01 | J66: 6.27 | K66: 14.3 | L66: 10.93 | M66: 2.09 | N66: Very High | O66: Above Avg. | P66: Direct | Q66: =I66*0.4+K66*0.5 -> 13.554 | R66: =(L66+J66)/2 -> 8.6 | S66: =(M66+K66)/2 -> 8.195 | T66: =('Investor-Inputs'!$G$19 * Q66) + ('Investor-Inputs'!$J$19 * R66) + ('Investor-Inputs'!$N$19 * S66) -> 66.057 | U66: =_xlfn.RANK.EQ(T66,$T$7:$T$592,0) -> 204
C67: Parag Parikh Flexi Cap Fund - Regular Plan | D67: 5 | E67: Unlock | F67: Equity: Flexi Cap | G67: 3.77 | H67: -1.46 | I67: 16.83 | J67: 9.27 | K67: 15.85 | L67: 13.27 | M67: 1.36 | N67: Very High | O67: Above Avg. | P67: Direct | Q67: =I67*0.4+K67*0.5 -> 14.657 | R67: =(L67+J67)/2 -> 11.27 | S67: =(M67+K67)/2 -> 8.605 | T67: =('Investor-Inputs'!$G$19 * Q67) + ('Investor-Inputs'!$J$19 * R67) + ('Investor-Inputs'!$N$19 * S67) -> 75.116 | U67: =_xlfn.RANK.EQ(T67,$T$7:$T$592,0) -> 158
C68: SBI Focused Fund | D68: 4 | E68: Unlock | F68: Equity: Flexi Cap | G68: 15.83 | H68: 15.25 | I68: 18.72 | J68: 14.78 | K68: 15.04 | L68: 14.29 | M68: 1.51 | N68: Very High | O68: Above Avg. | P68: Direct | Q68: =I68*0.4+K68*0.5 -> 15.008 | R68: =(L68+J68)/2 -> 14.535 | S68: =(M68+K68)/2 -> 8.275 | T68: =('Investor-Inputs'!$G$19 * Q68) + ('Investor-Inputs'!$J$19 * R68) + ('Investor-Inputs'!$N$19 * S68) -> 82.369 | U68: =_xlfn.RANK.EQ(T68,$T$7:$T$592,0) -> 122
C69: Union Retirement Fund - Regular Plan | D69: 4 | E69: Unlock | F69: Equity: Flexi Cap | G69: 7.5 | H69: 2.77 | I69: 16.7 | J69: 8.59 | M69: 2.42 | N69: Very High | O69: Above Avg. | P69: Direct | Q69: =I69*0.4+K69*0.5 -> 6.68 | R69: =(L69+J69)/2 -> 4.295 | S69: =(M69+K69)/2 -> 1.21 | T69: =('Investor-Inputs'!$G$19 * Q69) + ('Investor-Inputs'!$J$19 * R69) + ('Investor-Inputs'!$N$19 * S69) -> 29.84 | U69: =_xlfn.RANK.EQ(T69,$T$7:$T$592,0) -> 542
C70: WhiteOak Capital Flexi Cap Fund - Regular Plan | D70: 4 | E70: Unlock | F70: Equity: Flexi Cap | G70: 3.73 | H70: -1.94 | I70: 17.63 | J70: 8.34 | M70: 1.92 | N70: Very High | O70: Above Avg. | P70: Direct | Q70: =I70*0.4+K70*0.5 -> 7.052 | R70: =(L70+J70)/2 -> 4.17 | S70: =(M70+K70)/2 -> 0.96 | T70: =('Investor-Inputs'!$G$19 * Q70) + ('Investor-Inputs'!$J$19 * R70) + ('Investor-Inputs'!$N$19 * S70) -> 30.456 | U70: =_xlfn.RANK.EQ(T70,$T$7:$T$592,0) -> 516
C71: Axis Multicap Fund - Regular Plan | D71: 5 | E71: Unlock | F71: Equity: Multi Cap | G71: 7.22 | H71: 1.24 | I71: 21.3 | J71: 10.81 | M71: 2.29 | N71: Very High | O71: High | P71: Direct | Q71: =I71*0.4+K71*0.5 -> 8.52 | R71: =(L71+J71)/2 -> 5.405 | S71: =(M71+K71)/2 -> 1.145 | T71: =('Investor-Inputs'!$G$19 * Q71) + ('Investor-Inputs'!$J$19 * R71) + ('Investor-Inputs'!$N$19 * S71) -> 37.515 | U71: =_xlfn.RANK.EQ(T71,$T$7:$T$592,0) -> 335
C72: Bank of India Multi Cap Fund - Regular Plan | D72: 4 | E72: Unlock | F72: Equity: Multi Cap | G72: 13.77 | H72: 10.51 | I72: 21.12 | J72: 12.49 | M72: 2.24 | N72: Very High | O72: Above Avg. | P72: Direct | Q72: =I72*0.4+K72*0.5 -> 8.448 | R72: =(L72+J72)/2 -> 6.245 | S72: =(M72+K72)/2 -> 1.12 | T72: =('Investor-Inputs'!$G$19 * Q72) + ('Investor-Inputs'!$J$19 * R72) + ('Investor-Inputs'!$N$19 * S72) -> 38.954 | U72: =_xlfn.RANK.EQ(T72,$T$7:$T$592,0) -> 333
C73: HSBC Multi Cap Fund - Regular Plan | D73: 4 | E73: Unlock | F73: Equity: Multi Cap | G73: 9.74 | H73: 5.17 | I73: 22.24 | J73: 11.16 | M73: 2.22 | N73: Very High | O73: High | P73: Direct | Q73: =I73*0.4+K73*0.5 -> 8.896 | R73: =(L73+J73)/2 -> 5.58 | S73: =(M73+K73)/2 -> 1.11 | T73: =('Investor-Inputs'!$G$19 * Q73) + ('Investor-Inputs'!$J$19 * R73) + ('Investor-Inputs'!$N$19 * S73) -> 38.958 | U73: =_xlfn.RANK.EQ(T73,$T$7:$T$592,0) -> 331
C74: ICICI Prudential Multicap Fund | D74: 4 | E74: Unlock | F74: Equity: Multi Cap | G74: 7.74 | H74: 7.85 | I74: 20.31 | J74: 11.44 | K74: 17.83 | L74: 15.16 | M74: 2.02 | N74: Very High | O74: Avg. | P74: Direct | Q74: =I74*0.4+K74*0.5 -> 17.039 | R74: =(L74+J74)/2 -> 13.3 | S74: =(M74+K74)/2 -> 9.925 | T74: =('Investor-Inputs'!$G$19 * Q74) + ('Investor-Inputs'!$J$19 * R74) + ('Investor-Inputs'!$N$19 * S74) -> 87.642 | U74: =_xlfn.RANK.EQ(T74,$T$7:$T$592,0) -> 89
C75: Kotak Multicap Fund - Regular Plan | D75: 5 | E75: Unlock | F75: Equity: Multi Cap | G75: 11.15 | H75: 6.06 | I75: 22.8 | J75: 11.97 | M75: 1.64 | N75: Very High | O75: High | P75: Direct | Q75: =I75*0.4+K75*0.5 -> 9.12 | R75: =(L75+J75)/2 -> 5.985 | S75: =(M75+K75)/2 -> 0.82 | T75: =('Investor-Inputs'!$G$19 * Q75) + ('Investor-Inputs'!$J$19 * R75) + ('Investor-Inputs'!$N$19 * S75) -> 40.15 | U75: =_xlfn.RANK.EQ(T75,$T$7:$T$592,0) -> 325
C76: Mahindra Manulife Multi Cap Fund - Regular Plan | D76: 4 | E76: Unlock | F76: Equity: Multi Cap | G76: 10.06 | H76: 6.32 | I76: 20.36 | J76: 10.59 | K76: 17.84 | L76: 14.39 | M76: 2.91 | N76: Very High | O76: Above Avg. | P76: Direct | Q76: =I76*0.4+K76*0.5 -> 17.064 | R76: =(L76+J76)/2 -> 12.49 | S76: =(M76+K76)/2 -> 10.375 | T76: =('Investor-Inputs'!$G$19 * Q76) + ('Investor-Inputs'!$J$19 * R76) + ('Investor-Inputs'!$N$19 * S76) -> 86.547 | U76: =_xlfn.RANK.EQ(T76,$T$7:$T$592,0) -> 98
C77: Nippon India Multi Cap Fund | D77: 5 | E77: Unlock | F77: Equity: Multi Cap | G77: 7.19 | H77: 1.59 | I77: 20.32 | J77: 9.75 | K77: 21.31 | L77: 16.27 | M77: 1.47 | N77: Very High | O77: Above Avg. | P77: Direct | Q77: =I77*0.4+K77*0.5 -> 18.783 | R77: =(L77+J77)/2 -> 13.01 | S77: =(M77+K77)/2 -> 11.39 | T77: =('Investor-Inputs'!$G$19 * Q77) + ('Investor-Inputs'!$J$19 * R77) + ('Investor-Inputs'!$N$19 * S77) -> 93.759 | U77: =_xlfn.RANK.EQ(T77,$T$7:$T$592,0) -> 63
C78: Edelweiss Mid Cap Fund - Regular Plan | D78: 5 | E78: Unlock | F78: Equity: Mid Cap | G78: 10.73 | H78: 5.67 | I78: 24.72 | J78: 14.67 | K78: 21.02 | L78: 18.48 | M78: 1.8 | N78: Very High | O78: Above Avg. | P78: Direct | Q78: =I78*0.4+K78*0.5 -> 20.398 | R78: =(L78+J78)/2 -> 16.575 | S78: =(M78+K78)/2 -> 11.41 | T78: =('Investor-Inputs'!$G$19 * Q78) + ('Investor-Inputs'!$J$19 * R78) + ('Investor-Inputs'!$N$19 * S78) -> 105.754 | U78: =_xlfn.RANK.EQ(T78,$T$7:$T$592,0) -> 39
C79: HDFC Mid Cap Fund - Regular Plan | D79: 5 | E79: Unlock | F79: Equity: Mid Cap | G79: 10.69 | H79: 2.78 | I79: 23.56 | J79: 12.21 | K79: 21.25 | L79: 18.34 | M79: 1.3 | N79: Very High | O79: Above Avg. | P79: Direct | Q79: =I79*0.4+K79*0.5 -> 20.049 | R79: =(L79+J79)/2 -> 15.275 | S79: =(M79+K79)/2 -> 11.275 | T79: =('Investor-Inputs'!$G$19 * Q79) + ('Investor-Inputs'!$J$19 * R79) + ('Investor-Inputs'!$N$19 * S79) -> 101.972 | U79: =_xlfn.RANK.EQ(T79,$T$7:$T$592,0) -> 45
C80: ICICI Prudential Midcap Fund | D80: 4 | E80: Unlock | F80: Equity: Mid Cap | G80: 24.33 | H80: 19.63 | I80: 26.21 | J80: 18.78 | K80: 20.73 | L80: 19.6 | M80: 1.84 | N80: Very High | O80: Above Avg. | P80: Direct | Q80: =I80*0.4+K80*0.5 -> 20.849 | R80: =(L80+J80)/2 -> 19.19 | S80: =(M80+K80)/2 -> 11.285 | T80: =('Investor-Inputs'!$G$19 * Q80) + ('Investor-Inputs'!$J$19 * R80) + ('Investor-Inputs'!$N$19 * S80) -> 112.212 | U80: =_xlfn.RANK.EQ(T80,$T$7:$T$592,0) -> 25
C81: Invesco India Mid Cap Fund - Regular Plan | D81: 4 | E81: Unlock | F81: Equity: Mid Cap | G81: 13.6 | H81: 4.16 | I81: 25.59 | J81: 16.05 | K81: 21.01 | L81: 19.18 | M81: 2.17 | N81: Very High | O81: High | P81: Direct | Q81: =I81*0.4+K81*0.5 -> 20.741 | R81: =(L81+J81)/2 -> 17.615 | S81: =(M81+K81)/2 -> 11.59 | T81: =('Investor-Inputs'!$G$19 * Q81) + ('Investor-Inputs'!$J$19 * R81) + ('Investor-Inputs'!$N$19 * S81) -> 109.043 | U81: =_xlfn.RANK.EQ(T81,$T$7:$T$592,0) -> 33
C82: ITI Mid Cap Fund - Regular Plan | D82: 4 | E82: Unlock | F82: Equity: Mid Cap | G82: 11.39 | H82: 6.83 | I82: 23.61 | J82: 12.25 | K82: 16.78 | L82: 16.26 | M82: 1.84 | N82: Very High | O82: Above Avg. | P82: Direct | Q82: =I82*0.4+K82*0.5 -> 17.834 | R82: =(L82+J82)/2 -> 14.255 | S82: =(M82+K82)/2 -> 9.31 | T82: =('Investor-Inputs'!$G$19 * Q82) + ('Investor-Inputs'!$J$19 * R82) + ('Investor-Inputs'!$N$19 * S82) -> 91.322 | U82: =_xlfn.RANK.EQ(T82,$T$7:$T$592,0) -> 75
C83: JM Midcap Fund - Regular Plan | D83: 4 | E83: Unlock | F83: Equity: Mid Cap | G83: 7.09 | H83: 3.68 | I83: 23.26 | J83: 10.26 | M83: 2.31 | N83: Very High | O83: Above Avg. | P83: Direct | Q83: =I83*0.4+K83*0.5 -> 9.304 | R83: =(L83+J83)/2 -> 5.13 | S83: =(M83+K83)/2 -> 1.155 | T83: =('Investor-Inputs'!$G$19 * Q83) + ('Investor-Inputs'!$J$19 * R83) + ('Investor-Inputs'!$N$19 * S83) -> 39.327 | U83: =_xlfn.RANK.EQ(T83,$T$7:$T$592,0) -> 329
C84: Kotak Midcap Fund - Regular Plan | D84: 4 | E84: Unlock | F84: Equity: Mid Cap | G84: 13.91 | H84: 6.69 | I84: 21.47 | J84: 13.11 | K84: 18.88 | L84: 16.37 | M84: 1.45 | N84: Very High | O84: Avg. | P84: Direct | Q84: =I84*0.4+K84*0.5 -> 18.028 | R84: =(L84+J84)/2 -> 14.74 | S84: =(M84+K84)/2 -> 10.165 | T84: =('Investor-Inputs'!$G$19 * Q84) + ('Investor-Inputs'!$J$19 * R84) + ('Investor-Inputs'!$N$19 * S84) -> 93.729 | U84: =_xlfn.RANK.EQ(T84,$T$7:$T$592,0) -> 65
C85: Mahindra Manulife Mid Cap Fund - Regular Plan | D85: 4 | E85: Unlock | F85: Equity: Mid Cap | G85: 12.03 | H85: 11.03 | I85: 24.21 | J85: 13.27 | K85: 20.1 | L85: 17.7 | M85: 2.27 | N85: Very High | O85: Above Avg. | P85: Direct | Q85: =I85*0.4+K85*0.5 -> 19.734 | R85: =(L85+J85)/2 -> 15.485 | S85: =(M85+K85)/2 -> 11.185 | T85: =('Investor-Inputs'!$G$19 * Q85) + ('Investor-Inputs'!$J$19 * R85) + ('Investor-Inputs'!$N$19 * S85) -> 101.357 | U85: =_xlfn.RANK.EQ(T85,$T$7:$T$592,0) -> 47
C86: Motilal Oswal Midcap Fund - Regular Plan | D86: 4 | E86: Unlock | F86: Equity: Mid Cap | G86: -3.85 | H86: -12.01 | I86: 20.88 | J86: 6.03 | K86: 22.82 | L86: 15.79 | M86: 1.61 | N86: Very High | O86: High | P86: Direct | Q86: =I86*0.4+K86*0.5 -> 19.762 | R86: =(L86+J86)/2 -> 10.91 | S86: =(M86+K86)/2 -> 12.215 | T86: =('Investor-Inputs'!$G$19 * Q86) + ('Investor-Inputs'!$J$19 * R86) + ('Investor-Inputs'!$N$19 * S86) -> 93.321 | U86: =_xlfn.RANK.EQ(T86,$T$7:$T$592,0) -> 69
C87: Nippon India Growth Mid Cap Fund | D87: 5 | E87: Unlock | F87: Equity: Mid Cap | G87: 12.26 | H87: 8.88 | I87: 25.44 | J87: 14.46 | K87: 22.24 | L87: 19.04 | M87: 1.92 | N87: Very High | O87: High | P87: Direct | Q87: =I87*0.4+K87*0.5 -> 21.296 | R87: =(L87+J87)/2 -> 16.75 | S87: =(M87+K87)/2 -> 12.08 | T87: =('Investor-Inputs'!$G$19 * Q87) + ('Investor-Inputs'!$J$19 * R87) + ('Investor-Inputs'!$N$19 * S87) -> 109.468 | U87: =_xlfn.RANK.EQ(T87,$T$7:$T$592,0) -> 31
C88: Sundaram Mid Cap Fund - Regular Plan | D88: 4 | E88: Unlock | F88: Equity: Mid Cap | G88: 11.3 | H88: 5.56 | I88: 24.15 | J88: 13.44 | K88: 19.86 | L88: 17.61 | M88: 2.25 | N88: Very High | O88: Above Avg. | P88: Direct | Q88: =I88*0.4+K88*0.5 -> 19.59 | R88: =(L88+J88)/2 -> 15.525 | S88: =(M88+K88)/2 -> 11.055 | T88: =('Investor-Inputs'!$G$19 * Q88) + ('Investor-Inputs'!$J$19 * R88) + ('Investor-Inputs'!$N$19 * S88) -> 100.875 | U88: =_xlfn.RANK.EQ(T88,$T$7:$T$592,0) -> 49
C89: WhiteOak Capital Mid Cap Fund - Regular Plan | D89: 5 | E89: Unlock | F89: Equity: Mid Cap | G89: 15.16 | H89: 8.45 | I89: 25.61 | J89: 15.18 | M89: 2.02 | N89: Very High | O89: Above Avg. | P89: Direct | Q89: =I89*0.4+K89*0.5 -> 10.244 | R89: =(L89+J89)/2 -> 7.59 | S89: =(M89+K89)/2 -> 1.01 | T89: =('Investor-Inputs'!$G$19 * Q89) + ('Investor-Inputs'!$J$19 * R89) + ('Investor-Inputs'!$N$19 * S89) -> 46.922 | U89: =_xlfn.RANK.EQ(T89,$T$7:$T$592,0) -> 289
C90: Axis Nifty Smallcap 50 Index Fund - Regular Plan | D90: 4 | E90: Unlock | F90: Equity: Small Cap | G90: 10.08 | H90: 7.41 | I90: 24.27 | J90: 10.89 | M90: 1.05 | N90: Very High | O90: Above Avg. | P90: Direct | Q90: =I90*0.4+K90*0.5 -> 9.708 | R90: =(L90+J90)/2 -> 5.445 | S90: =(M90+K90)/2 -> 0.525 | T90: =('Investor-Inputs'!$G$19 * Q90) + ('Investor-Inputs'!$J$19 * R90) + ('Investor-Inputs'!$N$19 * S90) -> 40.539 | U90: =_xlfn.RANK.EQ(T90,$T$7:$T$592,0) -> 321
C91: Axis Small Cap Fund - Regular Plan | D91: 4 | E91: Unlock | F91: Equity: Small Cap | G91: 8.45 | H91: 4.16 | I91: 17.83 | J91: 8.85 | K91: 18.11 | L91: 13.47 | M91: 1.74 | N91: Very High | O91: Below Avg. | P91: Direct | Q91: =I91*0.4+K91*0.5 -> 16.187 | R91: =(L91+J91)/2 -> 11.16 | S91: =(M91+K91)/2 -> 9.925 | T91: =('Investor-Inputs'!$G$19 * Q91) + ('Investor-Inputs'!$J$19 * R91) + ('Investor-Inputs'!$N$19 * S91) -> 80.806 | U91: =_xlfn.RANK.EQ(T91,$T$7:$T$592,0) -> 128
C92: Bandhan Small Cap Fund - Regular Plan | D92: 5 | E92: Unlock | F92: Equity: Small Cap | G92: 13.73 | H92: 8.68 | I92: 30.4 | J92: 16.61 | K92: 22.81 | L92: 20.73 | M92: 1.98 | N92: Very High | O92: High | P92: Direct | Q92: =I92*0.4+K92*0.5 -> 23.565 | R92: =(L92+J92)/2 -> 18.67 | S92: =(M92+K92)/2 -> 12.395 | T92: =('Investor-Inputs'!$G$19 * Q92) + ('Investor-Inputs'!$J$19 * R92) + ('Investor-Inputs'!$N$19 * S92) -> 120.43 | U92: =_xlfn.RANK.EQ(T92,$T$7:$T$592,0) -> 13
C93: Edelweiss Small Cap Fund - Regular Plan | D93: 4 | E93: Unlock | F93: Equity: Small Cap | G93: 9.75 | H93: 4.15 | I93: 19.04 | J93: 8.69 | K93: 19.37 | L93: 14.24 | M93: 2.13 | N93: Very High | O93: Avg. | P93: Direct | Q93: =I93*0.4+K93*0.5 -> 17.301 | R93: =(L93+J93)/2 -> 11.465 | S93: =(M93+K93)/2 -> 10.75 | T93: =('Investor-Inputs'!$G$19 * Q93) + ('Investor-Inputs'!$J$19 * R93) + ('Investor-Inputs'!$N$19 * S93) -> 85.583 | U93: =_xlfn.RANK.EQ(T93,$T$7:$T$592,0) -> 108
C94: HDFC Small Cap Fund - Regular Plan | D94: 4 | E94: Unlock | F94: Equity: Small Cap | G94: 7.06 | H94: -5.28 | I94: 16.39 | J94: 4.86 | K94: 19.08 | L94: 12.77 | M94: 1.62 | N94: Very High | O94: Above Avg. | P94: Direct | Q94: =I94*0.4+K94*0.5 -> 16.096 | R94: =(L94+J94)/2 -> 8.815 | S94: =(M94+K94)/2 -> 10.35 | T94: =('Investor-Inputs'!$G$19 * Q94) + ('Investor-Inputs'!$J$19 * R94) + ('Investor-Inputs'!$N$19 * S94) -> 76.268 | U94: =_xlfn.RANK.EQ(T94,$T$7:$T$592,0) -> 150
C95: Invesco India Smallcap Fund - Regular Plan | D95: 5 | E95: Unlock | F95: Equity: Small Cap | G95: 11.15 | H95: 5.39 | I95: 24.12 | J95: 12.68 | K95: 21.78 | L95: 17.54 | M95: 1.93 | N95: Very High | O95: High | P95: Direct | Q95: =I95*0.4+K95*0.5 -> 20.538 | R95: =(L95+J95)/2 -> 15.11 | S95: =(M95+K95)/2 -> 11.855 | T95: =('Investor-Inputs'!$G$19 * Q95) + ('Investor-Inputs'!$J$19 * R95) + ('Investor-Inputs'!$N$19 * S95) -> 103.689 | U95: =_xlfn.RANK.EQ(T95,$T$7:$T$592,0) -> 41
C96: ITI Small Cap Fund - Regular Plan | D96: 4 | E96: Unlock | F96: Equity: Small Cap | G96: 12.21 | H96: 10.35 | I96: 25.17 | J96: 13.49 | K96: 17.59 | L96: 17.59 | M96: 1.95 | N96: Very High | O96: Above Avg. | P96: Direct | Q96: =I96*0.4+K96*0.5 -> 18.863 | R96: =(L96+J96)/2 -> 15.54 | S96: =(M96+K96)/2 -> 9.77 | T96: =('Investor-Inputs'!$G$19 * Q96) + ('Investor-Inputs'!$J$19 * R96) + ('Investor-Inputs'!$N$19 * S96) -> 97.439 | U96: =_xlfn.RANK.EQ(T96,$T$7:$T$592,0) -> 55
C97: Kotak Nifty Smallcap 50 Index Fund - Regular Plan | D97: 4 | E97: Unlock | F97: Equity: Small Cap | G97: 9.85 | H97: 7.03 | I97: 24.28 | J97: 10.96 | M97: 1.52 | N97: Very High | O97: Above Avg. | P97: Direct | Q97: =I97*0.4+K97*0.5 -> 9.712 | R97: =(L97+J97)/2 -> 5.48 | S97: =(M97+K97)/2 -> 0.76 | T97: =('Investor-Inputs'!$G$19 * Q97) + ('Investor-Inputs'!$J$19 * R97) + ('Investor-Inputs'!$N$19 * S97) -> 40.856 | U97: =_xlfn.RANK.EQ(T97,$T$7:$T$592,0) -> 315
C98: Mahindra Manulife Small Cap Fund - Regular Plan | D98: 4 | E98: Unlock | F98: Equity: Small Cap | G98: 13.69 | H98: 10.21 | I98: 24.06 | J98: 11.35 | M98: 2.96 | N98: Very High | O98: Above Avg. | P98: Direct | Q98: =I98*0.4+K98*0.5 -> 9.624 | R98: =(L98+J98)/2 -> 5.675 | S98: =(M98+K98)/2 -> 1.48 | T98: =('Investor-Inputs'!$G$19 * Q98) + ('Investor-Inputs'!$J$19 * R98) + ('Investor-Inputs'!$N$19 * S98) -> 41.702 | U98: =_xlfn.RANK.EQ(T98,$T$7:$T$592,0) -> 309
C99: Nippon India Small Cap Fund | D99: 4 | E99: Unlock | F99: Equity: Small Cap | G99: 10.36 | H99: 7.52 | I99: 21.1 | J99: 9.55 | K99: 22.34 | L99: 16.63 | M99: 1.5 | N99: Very High | O99: Above Avg. | P99: Direct | Q99: =I99*0.4+K99*0.5 -> 19.61 | R99: =(L99+J99)/2 -> 13.09 | S99: =(M99+K99)/2 -> 11.92 | T99: =('Investor-Inputs'!$G$19 * Q99) + ('Investor-Inputs'!$J$19 * R99) + ('Investor-Inputs'!$N$19 * S99) -> 96.93 | U99: =_xlfn.RANK.EQ(T99,$T$7:$T$592,0) -> 57
C100: Quant Small Cap Fund | D100: 4 | E100: Unlock | F100: Equity: Small Cap | G100: 8.43 | H100: 7.23 | I100: 20.13 | J100: 8.46 | K100: 21.82 | L100: 15.83 | M100: 2.02 | N100: Very High | O100: High | P100: Direct | Q100: =I100*0.4+K100*0.5 -> 18.962 | R100: =(L100+J100)/2 -> 12.145 | S100: =(M100+K100)/2 -> 11.92 | T100: =('Investor-Inputs'!$G$19 * Q100) + ('Investor-Inputs'!$J$19 * R100) + ('Investor-Inputs'!$N$19 * S100) -> 93.096 | U100: =_xlfn.RANK.EQ(T100,$T$7:$T$592,0) -> 73
C101: Sundaram Small Cap Fund - Regular Plan | D101: 4 | E101: Unlock | F101: Equity: Small Cap | G101: 15.74 | H101: 12.23 | I101: 20.48 | J101: 11.42 | K101: 19.42 | L101: 15.46 | M101: 1.91 | N101: Very High | O101: Avg. | P101: Direct | Q101: =I101*0.4+K101*0.5 -> 17.902 | R101: =(L101+J101)/2 -> 13.44 | S101: =(M101+K101)/2 -> 10.665 | T101: =('Investor-Inputs'!$G$19 * Q101) + ('Investor-Inputs'!$J$19 * R101) + ('Investor-Inputs'!$N$19 * S101) -> 91.251 | U101: =_xlfn.RANK.EQ(T101,$T$7:$T$592,0) -> 77
C102: Axis Value Fund - Regular Plan | D102: 4 | E102: Unlock | F102: Equity: Value Oriented | G102: 7.95 | H102: 2.57 | I102: 20.8 | J102: 10.98 | M102: 2.55 | N102: Very High | O102: Above Avg. | P102: Direct | Q102: =I102*0.4+K102*0.5 -> 8.32 | R102: =(L102+J102)/2 -> 5.49 | S102: =(M102+K102)/2 -> 1.275 | T102: =('Investor-Inputs'!$G$19 * Q102) + ('Investor-Inputs'!$J$19 * R102) + ('Investor-Inputs'!$N$19 * S102) -> 37.215 | U102: =_xlfn.RANK.EQ(T102,$T$7:$T$592,0) -> 339
C103: Bandhan Value Fund - Regular Plan | D103: 4 | E103: Unlock | F103: Equity: Value Oriented | G103: 1.38 | H103: -2.01 | I103: 15.19 | J103: 5.58 | K103: 16.44 | L103: 11.3 | M103: 2.1 | N103: Very High | O103: Avg. | P103: Direct | Q103: =I103*0.4+K103*0.5 -> 14.296 | R103: =(L103+J103)/2 -> 8.44 | S103: =(M103+K103)/2 -> 9.27 | T103: =('Investor-Inputs'!$G$19 * Q103) + ('Investor-Inputs'!$J$19 * R103) + ('Investor-Inputs'!$N$19 * S103) -> 69.038 | U103: =_xlfn.RANK.EQ(T103,$T$7:$T$592,0) -> 194
C104: DSP Value Fund - Regular Plan | D104: 5 | E104: Unlock | F104: Equity: Value Oriented | G104: 15.03 | H104: 10.36 | I104: 19.21 | J104: 13.9 | K104: 15.01 | L104: 15.12 | M104: 1.94 | N104: Very High | O104: Avg. | P104: Direct | Q104: =I104*0.4+K104*0.5 -> 15.189 | R104: =(L104+J104)/2 -> 14.51 | S104: =(M104+K104)/2 -> 8.475 | T104: =('Investor-Inputs'!$G$19 * Q104) + ('Investor-Inputs'!$J$19 * R104) + ('Investor-Inputs'!$N$19 * S104) -> 83.062 | U104: =_xlfn.RANK.EQ(T104,$T$7:$T$592,0) -> 116
C105: HSBC Value Fund | D105: 4 | E105: Unlock | F105: Equity: Value Oriented | G105: 10.09 | H105: 4.37 | I105: 21.67 | J105: 11.81 | K105: 19.47 | L105: 16.66 | M105: 1.71 | N105: Very High | O105: High | P105: Direct | Q105: =I105*0.4+K105*0.5 -> 18.403 | R105: =(L105+J105)/2 -> 14.235 | S105: =(M105+K105)/2 -> 10.59 | T105: =('Investor-Inputs'!$G$19 * Q105) + ('Investor-Inputs'!$J$19 * R105) + ('Investor-Inputs'!$N$19 * S105) -> 94.269 | U105: =_xlfn.RANK.EQ(T105,$T$7:$T$592,0) -> 59
...

Sheet mf_charts
C6: Fund Name | D6: Rating | E6: VR Opinion | F6: Category | G6: 1 Year Returns (%) | H6: 1 Year SIP Returns (%) | I6: 3 Year Returns (%) | J6: 3 Year SIP Returns (%) | K6: 5 Year Returns (%) | L6: 5 Year SIP Returns (%) | M6: Expense Ratio (%) | N6: Riskometer | O6: Return Grade | P6: Plan | Q6: ReturnScore | R6: SIPScore | S6: CostScore | T6: MFScore | U6: Rank
C7: Aditya Birla Sun Life Large Cap Fund - Regular Plan | D7: 4 | E7: Unlock | F7: Equity: Large Cap | G7: -0.47 | H7: -6.31 | I7: 13.07 | J7: 5.14 | K7: 12.5 | L7: 9.15 | M7: 1.58 | N7: Very High | O7: Above Avg. | P7: Direct | Q7: =I7*0.4+K7*0.5 -> 11.478 | R7: =(L7+J7)/2 -> 7.145 | S7: =(M7+K7)/2 -> 7.04 | T7: =('Investor-Inputs'!$G$19 * Q7) + ('Investor-Inputs'!$J$19 * R7) + ('Investor-Inputs'!$N$19 * S7) -> 55.764 | U7: =_xlfn.RANK.EQ(T7,$T$7:$T$592,0) -> 256
C8: Aditya Birla Sun Life Nifty 50 Equal Weight Index Fund - Regular Plan | D8: 4 | E8: Unlock | F8: Equity: Large Cap | G8: 6.69 | H8: 2.58 | I8: 15.81 | J8: 8.65 | M8: 1.1 | N8: Very High | O8: Above Avg. | P8: Direct | Q8: =I8*0.4+K8*0.5 -> 6.324 | R8: =(L8+J8)/2 -> 4.325 | S8: =(M8+K8)/2 -> 0.55 | T8: =('Investor-Inputs'!$G$19 * Q8) + ('Investor-Inputs'!$J$19 * R8) + ('Investor-Inputs'!$N$19 * S8) -> 28.172 | U8: =_xlfn.RANK.EQ(T8,$T$7:$T$592,0) -> 554
C9: Aditya Birla Sun Life Nifty Next 50 Index Fund - Regular Plan | D9: 4 | E9: Unlock | F9: Equity: Large Cap | G9: 8.12 | H9: 6.8 | I9: 20.35 | J9: 10.29 | M9: 0.89 | N9: Very High | O9: Above Avg. | P9: Direct | Q9: =I9*0.4+K9*0.5 -> 8.14 | R9: =(L9+J9)/2 -> 5.145 | S9: =(M9+K9)/2 -> 0.445 | T9: =('Investor-Inputs'!$G$19 * Q9) + ('Investor-Inputs'!$J$19 * R9) + ('Investor-Inputs'!$N$19 * S9) -> 35.155 | U9: =_xlfn.RANK.EQ(T9,$T$7:$T$592,0) -> 389
C10: Bandhan Large Cap Fund - Regular Plan | D10: 4 | E10: Unlock | F10: Equity: Large Cap | G10: 2.79 | H10: -2.89 | I10: 14.78 | J10: 7.14 | K10: 12.89 | L10: 10.4 | M10: 2.24 | N10: Very High | O10: Above Avg. | P10: Direct | Q10: =I10*0.4+K10*0.5 -> 12.357 | R10: =(L10+J10)/2 -> 8.77 | S10: =(M10+K10)/2 -> 7.565 | T10: =('Investor-Inputs'!$G$19 * Q10) + ('Investor-Inputs'!$J$19 * R10) + ('Investor-Inputs'!$N$19 * S10) -> 62.176 | U10: =_xlfn.RANK.EQ(T10,$T$7:$T$592,0) -> 226
C11: Baroda BNP Paribas Large Cap Fund - Regular Plan | D11: 4 | E11: Unlock | F11: Equity: Large Cap | G11: 2.57 | H11: -0.27 | I11: 14.44 | J11: 6.72 | K11: 13.07 | L11: 10.53 | M11: 2 | N11: Very High | O11: Above Avg. | P11: Direct | Q11: =I11*0.4+K11*0.5 -> 12.311 | R11: =(L11+J11)/2 -> 8.625 | S11: =(M11+K11)/2 -> 7.535 | T11: =('Investor-Inputs'!$G$19 * Q11) + ('Investor-Inputs'!$J$19 * R11) + ('Investor-Inputs'!$N$19 * S11) -> 61.718 | U11: =_xlfn.RANK.EQ(T11,$T$7:$T$592,0) -> 230
C12: Canara Robeco Large Cap Fund - Regular Plan | D12: 4 | E12: Unlock | F12: Equity: Large Cap | G12: -1.43 | H12: -6.93 | I12: 12.6 | J12: 4.99 | K12: 11.37 | L12: 8.71 | M12: 1.75 | N12: Very High | O12: Avg. | P12: Direct | Q12: =I12*0.4+K12*0.5 -> 10.725 | R12: =(L12+J12)/2 -> 6.85 | S12: =(M12+K12)/2 -> 6.56 | T12: =('Investor-Inputs'!$G$19 * Q12) + ('Investor-Inputs'!$J$19 * R12) + ('Investor-Inputs'!$N$19 * S12) -> 52.435 | U12: =_xlfn.RANK.EQ(T12,$T$7:$T$592,0) -> 275
C13: DSP Large Cap Fund - Regular Plan | D13: 5 | E13: Unlock | F13: Equity: Large Cap | G13: -2.41 | H13: -6.84 | I13: 15.09 | J13: 6.23 | K13: 12.28 | L13: 10.35 | M13: 2.52 | N13: Very High | O13: Above Avg. | P13: Direct | Q13: =I13*0.4+K13*0.5 -> 12.176 | R13: =(L13+J13)/2 -> 8.29 | S13: =(M13+K13)/2 -> 7.4 | T13: =('Investor-Inputs'!$G$19 * Q13) + ('Investor-Inputs'!$J$19 * R13) + ('Investor-Inputs'!$N$19 * S13) -> 60.508 | U13: =_xlfn.RANK.EQ(T13,$T$7:$T$592,0) -> 236
C14: DSP Nifty 50 Equal Weight Index Fund - Regular Plan | D14: 5 | E14: Unlock | F14: Equity: Large Cap | G14: 6.81 | H14: 2.67 | I14: 15.95 | J14: 8.77 | K14: 14.83 | L14: 12.24 | M14: 0.95 | N14: Very High | O14: Above Avg. | P14: Direct | Q14: =I14*0.4+K14*0.5 -> 13.795 | R14: =(L14+J14)/2 -> 10.505 | S14: =(M14+K14)/2 -> 7.89 | T14: =('Investor-Inputs'!$G$19 * Q14) + ('Investor-Inputs'!$J$19 * R14) + ('Investor-Inputs'!$N$19 * S14) -> 70.285 | U14: =_xlfn.RANK.EQ(T14,$T$7:$T$592,0) -> 192
C15: DSP Nifty Next 50 Index Fund - Regular Plan | D15: 4 | E15: Unlock | F15: Equity: Large Cap | G15: 8.35 | H15: 6.86 | I15: 20.83 | J15: 10.65 | K15: 15.1 | L15: 13.33 | M15: 0.98 | N15: Very High | O15: High | P15: Direct | Q15: =I15*0.4+K15*0.5 -> 15.882 | R15: =(L15+J15)/2 -> 11.99 | S15: =(M15+K15)/2 -> 8.04 | T15: =('Investor-Inputs'!$G$19 * Q15) + ('Investor-Inputs'!$J$19 * R15) + ('Investor-Inputs'!$N$19 * S15) -> 79.666 | U15: =_xlfn.RANK.EQ(T15,$T$7:$T$592,0) -> 132
C16: Edelweiss Large Cap Fund - Regular Plan | D16: 4 | E16: Unlock | F16: Equity: Large Cap | G16: -0.09 | H16: -5.13 | I16: 12.29 | J16: 4.59 | K16: 12.11 | L16: 9 | M16: 2.12 | N16: Very High | O16: Avg. | P16: Direct | Q16: =I16*0.4+K16*0.5 -> 10.971 | R16: =(L16+J16)/2 -> 6.795 | S16: =(M16+K16)/2 -> 7.115 | T16: =('Investor-Inputs'!$G$19 * Q16) + ('Investor-Inputs'!$J$19 * R16) + ('Investor-Inputs'!$N$19 * S16) -> 53.618 | U16: =_xlfn.RANK.EQ(T16,$T$7:$T$592,0) -> 273
C17: HDFC Large Cap Fund - Regular Plan | D17: 5 | E17: Unlock | F17: Equity: Large Cap | G17: -1.59 | H17: -6.6 | I17: 12.48 | J17: 3.95 | K17: 13.84 | L17: 9.59 | M17: 1.58 | N17: Very High | O17: Above Avg. | P17: Direct | Q17: =I17*0.4+K17*0.5 -> 11.912 | R17: =(L17+J17)/2 -> 6.77 | S17: =(M17+K17)/2 -> 7.71 | T17: =('Investor-Inputs'!$G$19 * Q17) + ('Investor-Inputs'!$J$19 * R17) + ('Investor-Inputs'!$N$19 * S17) -> 56.986 | U17: =_xlfn.RANK.EQ(T17,$T$7:$T$592,0) -> 246
C18: HDFC NIFTY 100 Equal Weight Index Fund - Regular Plan | D18: 4 | E18: Unlock | F18: Equity: Large Cap | G18: 7.88 | H18: 4.9 | I18: 18.08 | J18: 9.68 | M18: 0.88 | N18: Very High | O18: Above Avg. | P18: Direct | Q18: =I18*0.4+K18*0.5 -> 7.232 | R18: =(L18+J18)/2 -> 4.84 | S18: =(M18+K18)/2 -> 0.44 | T18: =('Investor-Inputs'!$G$19 * Q18) + ('Investor-Inputs'!$J$19 * R18) + ('Investor-Inputs'!$N$19 * S18) -> 31.816 | U18: =_xlfn.RANK.EQ(T18,$T$7:$T$592,0) -> 504
C19: HDFC NIFTY50 Equal Weight Index Fund - Regular Plan | D19: 5 | E19: Unlock | F19: Equity: Large Cap | G19: 6.85 | H19: 2.71 | I19: 16.02 | J19: 8.85 | M19: 1 | N19: Very High | O19: Above Avg. | P19: Direct | Q19: =I19*0.4+K19*0.5 -> 6.408 | R19: =(L19+J19)/2 -> 4.425 | S19: =(M19+K19)/2 -> 0.5 | T19: =('Investor-Inputs'!$G$19 * Q19) + ('Investor-Inputs'!$J$19 * R19) + ('Investor-Inputs'!$N$19 * S19) -> 28.574 | U19: =_xlfn.RANK.EQ(T19,$T$7:$T$592,0) -> 546
C20: ICICI Prudential BHARAT 22 FOF | D20: 5 | E20: Unlock | F20: Equity: Large Cap | G20: 17.4 | H20: 18.98 | I20: 25.53 | J20: 16.37 | K20: 28 | L20: 23.73 | M20: 0.14 | N20: Very High | O20: High | P20: Direct | Q20: =I20*0.4+K20*0.5 -> 24.212 | R20: =(L20+J20)/2 -> 20.05 | S20: =(M20+K20)/2 -> 14.07 | T20: =('Investor-Inputs'!$G$19 * Q20) + ('Investor-Inputs'!$J$19 * R20) + ('Investor-Inputs'!$N$19 * S20) -> 126.806 | U20: =_xlfn.RANK.EQ(T20,$T$7:$T$592,0) -> 7
C21: ICICI Prudential Large Cap Fund | D21: 5 | E21: Unlock | F21: Equity: Large Cap | G21: 0.07 | H21: -5.94 | I21: 15.26 | J21: 6.51 | K21: 14.67 | L21: 11.25 | M21: 3.59 | N21: Very High | O21: Above Avg. | P21: Direct | Q21: =I21*0.4+K21*0.5 -> 13.439 | R21: =(L21+J21)/2 -> 8.88 | S21: =(M21+K21)/2 -> 9.13 | T21: =('Investor-Inputs'!$G$19 * Q21) + ('Investor-Inputs'!$J$19 * R21) + ('Investor-Inputs'!$N$19 * S21) -> 67.207 | U21: =_xlfn.RANK.EQ(T21,$T$7:$T$592,0) -> 202
C22: ICICI Prudential Nifty 100 Low Volatility 30 ETF FOF | D22: 4 | E22: Unlock | F22: Equity: Large Cap | G22: 1.08 | H22: -4.13 | I22: 13.56 | J22: 5.49 | K22: 12.11 | L22: 9.43 | M22: 0.58 | N22: Very High | O22: Avg. | P22: Direct | Q22: =I22*0.4+K22*0.5 -> 11.479 | R22: =(L22+J22)/2 -> 7.46 | S22: =(M22+K22)/2 -> 6.345 | T22: =('Investor-Inputs'!$G$19 * Q22) + ('Investor-Inputs'!$J$19 * R22) + ('Investor-Inputs'!$N$19 * S22) -> 55.702 | U22: =_xlfn.RANK.EQ(T22,$T$7:$T$592,0) -> 258
C23: ICICI Prudential Nifty50 Equal Weight Index Fund | D23: 4 | E23: Unlock | F23: Equity: Large Cap | G23: 6.65 | H23: 2.53 | I23: 15.8 | J23: 8.67 | M23: 1.25 | N23: Very High | O23: Above Avg. | P23: Direct | Q23: =I23*0.4+K23*0.5 -> 6.32 | R23: =(L23+J23)/2 -> 4.335 | S23: =(M23+K23)/2 -> 0.625 | T23: =('Investor-Inputs'!$G$19 * Q23) + ('Investor-Inputs'!$J$19 * R23) + ('Investor-Inputs'!$N$19 * S23) -> 28.255 | U23: =_xlfn.RANK.EQ(T23,$T$7:$T$592,0) -> 552
C24: Invesco India Largecap Fund - Regular Plan | D24: 4 | E24: Unlock | F24: Equity: Large Cap | G24: 2.12 | H24: -3.12 | I24: 15.53 | J24: 7 | K24: 13.55 | L24: 10.5 | M24: 2.08 | N24: Very High | O24: Above Avg. | P24: Direct | Q24: =I24*0.4+K24*0.5 -> 12.987 | R24: =(L24+J24)/2 -> 8.75 | S24: =(M24+K24)/2 -> 7.815 | T24: =('Investor-Inputs'!$G$19 * Q24) + ('Investor-Inputs'!$J$19 * R24) + ('Investor-Inputs'!$N$19 * S24) -> 64.276 | U24: =_xlfn.RANK.EQ(T24,$T$7:$T$592,0) -> 212
C25: Kotak Large Cap Fund - Regular Plan | D25: 4 | E25: Unlock | F25: Equity: Large Cap | G25: 0.86 | H25: -5.19 | I25: 12.92 | J25: 5.64 | K25: 12.12 | L25: 9.24 | M25: 1.89 | N25: Very High | O25: Avg. | P25: Direct | Q25: =I25*0.4+K25*0.5 -> 11.228 | R25: =(L25+J25)/2 -> 7.44 | S25: =(M25+K25)/2 -> 7.005 | T25: =('Investor-Inputs'!$G$19 * Q25) + ('Investor-Inputs'!$J$19 * R25) + ('Investor-Inputs'!$N$19 * S25) -> 55.569 | U25: =_xlfn.RANK.EQ(T25,$T$7:$T$592,0) -> 262
C26: Kotak Nifty Next 50 Index Fund - Regular Plan | D26: 4 | E26: Unlock | F26: Equity: Large Cap | G26: 8.33 | H26: 6.98 | I26: 20.72 | J26: 10.66 | K26: 15.03 | L26: 13.29 | M26: 0.9 | N26: Very High | O26: High | P26: Direct | Q26: =I26*0.4+K26*0.5 -> 15.803 | R26: =(L26+J26)/2 -> 11.975 | S26: =(M26+K26)/2 -> 7.965 | T26: =('Investor-Inputs'!$G$19 * Q26) + ('Investor-Inputs'!$J$19 * R26) + ('Investor-Inputs'!$N$19 * S26) -> 79.324 | U26: =_xlfn.RANK.EQ(T26,$T$7:$T$592,0) -> 134
C27: Mirae Asset Diversified Equity Allocator Passive FoF - Regular Plan | D27: 4 | E27: Unlock | F27: Equity: Large Cap | G27: 3.38 | H27: -1.33 | I27: 14.48 | J27: 6.77 | K27: 13.29 | L27: 10.45 | M27: 0.11 | N27: Very High | O27: Above Avg. | P27: Direct | Q27: =I27*0.4+K27*0.5 -> 12.437 | R27: =(L27+J27)/2 -> 8.61 | S27: =(M27+K27)/2 -> 6.7 | T27: =('Investor-Inputs'!$G$19 * Q27) + ('Investor-Inputs'!$J$19 * R27) + ('Investor-Inputs'!$N$19 * S27) -> 61.231 | U27: =_xlfn.RANK.EQ(T27,$T$7:$T$592,0) -> 232
C28: Navi Nifty Next 50 Index Fund - Regular Plan | D28: 4 | E28: Unlock | F28: Equity: Large Cap | G28: 7.86 | H28: 6.38 | I28: 20.48 | J28: 10.34 | M28: 1.07 | N28: Very High | O28: Above Avg. | P28: Direct | Q28: =I28*0.4+K28*0.5 -> 8.192 | R28: =(L28+J28)/2 -> 5.17 | S28: =(M28+K28)/2 -> 0.535 | T28: =('Investor-Inputs'!$G$19 * Q28) + ('Investor-Inputs'!$J$19 * R28) + ('Investor-Inputs'!$N$19 * S28) -> 35.451 | U28: =_xlfn.RANK.EQ(T28,$T$7:$T$592,0) -> 383
C29: Nippon India Large Cap Fund | D29: 5 | E29: Unlock | F29: Equity: Large Cap | G29: 3.05 | H29: -3.29 | I29: 16.16 | J29: 7.34 | K29: 17.08 | L29: 12.88 | M29: 2.08 | N29: Very High | O29: Above Avg. | P29: Direct | Q29: =I29*0.4+K29*0.5 -> 15.004 | R29: =(L29+J29)/2 -> 10.11 | S29: =(M29+K29)/2 -> 9.58 | T29: =('Investor-Inputs'!$G$19 * Q29) + ('Investor-Inputs'!$J$19 * R29) + ('Investor-Inputs'!$N$19 * S29) -> 74.812 | U29: =_xlfn.RANK.EQ(T29,$T$7:$T$592,0) -> 162
C30: Nippon India Nifty Next 50 Junior BeES FoF - Regular Plan | D30: 4 | E30: Unlock | F30: Equity: Large Cap | G30: 9.02 | H30: 7.57 | I30: 21.18 | J30: 11.12 | K30: 15.23 | L30: 13.65 | M30: 0.3 | N30: Very High | O30: High | P30: Direct | Q30: =I30*0.4+K30*0.5 -> 16.087 | R30: =(L30+J30)/2 -> 12.385 | S30: =(M30+K30)/2 -> 7.765 | T30: =('Investor-Inputs'!$G$19 * Q30) + ('Investor-Inputs'!$J$19 * R30) + ('Investor-Inputs'!$N$19 * S30) -> 80.796 | U30: =_xlfn.RANK.EQ(T30,$T$7:$T$592,0) -> 130
C31: SBI Large Cap Fund | D31: 4 | E31: Unlock | F31: Equity: Large Cap | G31: 2.32 | H31: -2.17 | I31: 12.03 | J31: 6.1 | K31: 12.24 | L31: 9.46 | M31: 1.47 | N31: Very High | O31: Avg. | P31: Direct | Q31: =I31*0.4+K31*0.5 -> 10.932 | R31: =(L31+J31)/2 -> 7.78 | S31: =(M31+K31)/2 -> 6.855 | T31: =('Investor-Inputs'!$G$19 * Q31) + ('Investor-Inputs'!$J$19 * R31) + ('Investor-Inputs'!$N$19 * S31) -> 55.211 | U31: =_xlfn.RANK.EQ(T31,$T$7:$T$592,0) -> 268
C32: SBI Nifty Next 50 Index Fund - Regular Plan | D32: 5 | E32: Unlock | F32: Equity: Large Cap | G32: 8.24 | H32: 6.83 | I32: 20.71 | J32: 10.59 | M32: 0.71 | N32: Very High | O32: High | P32: Direct | Q32: =I32*0.4+K32*0.5 -> 8.284 | R32: =(L32+J32)/2 -> 5.295 | S32: =(M32+K32)/2 -> 0.355 | T32: =('Investor-Inputs'!$G$19 * Q32) + ('Investor-Inputs'!$J$19 * R32) + ('Investor-Inputs'!$N$19 * S32) -> 35.797 | U32: =_xlfn.RANK.EQ(T32,$T$7:$T$592,0) -> 359
C33: Sundaram Nifty 100 Equal Weight Fund | D33: 4 | E33: Unlock | F33: Equity: Large Cap | G33: 7.83 | H33: 5.02 | I33: 17.79 | J33: 9.55 | K33: 14.25 | L33: 12.35 | M33: 1.06 | N33: Very High | O33: Above Avg. | P33: Direct | Q33: =I33*0.4+K33*0.5 -> 14.241 | R33: =(L33+J33)/2 -> 10.95 | S33: =(M33+K33)/2 -> 7.655 | T33: =('Investor-Inputs'!$G$19 * Q33) + ('Investor-Inputs'!$J$19 * R33) + ('Investor-Inputs'!$N$19 * S33) -> 72.278 | U33: =_xlfn.RANK.EQ(T33,$T$7:$T$592,0) -> 182
C34: Tata Large Cap Fund - Regular Plan | D34: 4 | E34: Unlock | F34: Equity: Large Cap | G34: 2.52 | H34: -1.62 | I34: 13.25 | J34: 6.04 | K34: 12.53 | L34: 9.59 | M34: 2.33 | N34: Very High | O34: Above Avg. | P34: Direct | Q34: =I34*0.4+K34*0.5 -> 11.565 | R34: =(L34+J34)/2 -> 7.815 | S34: =(M34+K34)/2 -> 7.43 | T34: =('Investor-Inputs'!$G$19 * Q34) + ('Investor-Inputs'!$J$19 * R34) + ('Investor-Inputs'!$N$19 * S34) -> 57.755 | U34: =_xlfn.RANK.EQ(T34,$T$7:$T$592,0) -> 244
C35: WhiteOak Capital Large Cap Fund - Regular Plan | D35: 4 | E35: Unlock | F35: Equity: Large Cap | G35: 1.28 | H35: -4.43 | I35: 15.01 | J35: 7.07 | M35: 2.63 | N35: Very High | O35: Above Avg. | P35: Direct | Q35: =I35*0.4+K35*0.5 -> 6.004 | R35: =(L35+J35)/2 -> 3.535 | S35: =(M35+K35)/2 -> 1.315 | T35: =('Investor-Inputs'!$G$19 * Q35) + ('Investor-Inputs'!$J$19 * R35) + ('Investor-Inputs'!$N$19 * S35) -> 26.397 | U35: =_xlfn.RANK.EQ(T35,$T$7:$T$592,0) -> 566
C36: Bandhan Large & Mid Cap Fund - Regular Plan | D36: 5 | E36: Unlock | F36: Equity: Large & MidCap | G36: 9.77 | H36: 5.76 | I36: 23.13 | J36: 13.09 | K36: 19.12 | L36: 17.22 | M36: 2.9 | N36: Very High | O36: High | P36: Direct | Q36: =I36*0.4+K36*0.5 -> 18.812 | R36: =(L36+J36)/2 -> 15.155 | S36: =(M36+K36)/2 -> 11.01 | T36: =('Investor-Inputs'!$G$19 * Q36) + ('Investor-Inputs'!$J$19 * R36) + ('Investor-Inputs'!$N$19 * S36) -> 97.756 | U36: =_xlfn.RANK.EQ(T36,$T$7:$T$592,0) -> 53
C37: DSP Large & Mid Cap Fund - Regular Plan | D37: 4 | E37: Unlock | F37: Equity: Large & MidCap | G37: 1.71 | H37: -3 | I37: 18.4 | J37: 8.3 | K37: 15.02 | L37: 12.74 | M37: 2.12 | N37: Very High | O37: Above Avg. | P37: Direct | Q37: =I37*0.4+K37*0.5 -> 14.87 | R37: =(L37+J37)/2 -> 10.52 | S37: =(M37+K37)/2 -> 8.57 | T37: =('Investor-Inputs'!$G$19 * Q37) + ('Investor-Inputs'!$J$19 * R37) + ('Investor-Inputs'!$N$19 * S37) -> 74.22 | U37: =_xlfn.RANK.EQ(T37,$T$7:$T$592,0) -> 166
C38: HDFC Large and Mid Cap Fund - Regular Plan | D38: 4 | E38: Unlock | F38: Equity: Large & MidCap | G38: 3.83 | H38: -2.27 | I38: 17.9 | J38: 7.49 | K38: 17.56 | L38: 13.3 | M38: 1.59 | N38: Very High | O38: Above Avg. | P38: Direct | Q38: =I38*0.4+K38*0.5 -> 15.94 | R38: =(L38+J38)/2 -> 10.395 | S38: =(M38+K38)/2 -> 9.575 | T38: =('Investor-Inputs'!$G$19 * Q38) + ('Investor-Inputs'!$J$19 * R38) + ('Investor-Inputs'!$N$19 * S38) -> 78.185 | U38: =_xlfn.RANK.EQ(T38,$T$7:$T$592,0) -> 142
C39: ICICI Prudential Large & Mid Cap Fund | D39: 5 | E39: Unlock | F39: Equity: Large & MidCap | G39: 4.76 | H39: -0.1 | I39: 19.51 | J39: 10.55 | K39: 19.35 | L39: 15.25 | M39: 2.32 | N39: Very High | O39: Above Avg. | P39: Direct | Q39: =I39*0.4+K39*0.5 -> 17.479 | R39: =(L39+J39)/2 -> 12.9 | S39: =(M39+K39)/2 -> 10.835 | T39: =('Investor-Inputs'!$G$19 * Q39) + ('Investor-Inputs'!$J$19 * R39) + ('Investor-Inputs'!$N$19 * S39) -> 89.072 | U39: =_xlfn.RANK.EQ(T39,$T$7:$T$592,0) -> 83
C40: Invesco India Large & Mid Cap Fund - Regular Plan | D40: 4 | E40: Unlock | F40: Equity: Large & MidCap | G40: 8.69 | H40: 0.98 | I40: 23.14 | J40: 13.51 | K40: 17.71 | L40: 16.59 | M40: 1.9 | N40: Very High | O40: High | P40: Direct | Q40: =I40*0.4+K40*0.5 -> 18.111 | R40: =(L40+J40)/2 -> 15.05 | S40: =(M40+K40)/2 -> 9.805 | T40: =('Investor-Inputs'!$G$19 * Q40) + ('Investor-Inputs'!$J$19 * R40) + ('Investor-Inputs'!$N$19 * S40) -> 94.238 | U40: =_xlfn.RANK.EQ(T40,$T$7:$T$592,0) -> 61
C41: Motilal Oswal Large and Midcap Fund - Regular Plan | D41: 4 | E41: Unlock | F41: Equity: Large & MidCap | G41: 15.63 | H41: 9.31 | I41: 25.52 | J41: 15.88 | K41: 20.97 | L41: 19.38 | M41: 1.91 | N41: Very High | O41: High | P41: Direct | Q41: =I41*0.4+K41*0.5 -> 20.693 | R41: =(L41+J41)/2 -> 17.63 | S41: =(M41+K41)/2 -> 11.44 | T41: =('Investor-Inputs'!$G$19 * Q41) + ('Investor-Inputs'!$J$19 * R41) + ('Investor-Inputs'!$N$19 * S41) -> 108.779 | U41: =_xlfn.RANK.EQ(T41,$T$7:$T$592,0) -> 35
C42: Nippon India Vision Large & Mid Cap Fund | D42: 4 | E42: Unlock | F42: Equity: Large & MidCap | G42: 3.77 | H42: -0.43 | I42: 19.32 | J42: 9.72 | K42: 16.65 | L42: 13.98 | M42: 1.8 | N42: Very High | O42: Above Avg. | P42: Direct | Q42: =I42*0.4+K42*0.5 -> 16.053 | R42: =(L42+J42)/2 -> 11.85 | S42: =(M42+K42)/2 -> 9.225 | T42: =('Investor-Inputs'!$G$19 * Q42) + ('Investor-Inputs'!$J$19 * R42) + ('Investor-Inputs'!$N$19 * S42) -> 81.084 | U42: =_xlfn.RANK.EQ(T42,$T$7:$T$592,0) -> 124
C43: SBI Large & Midcap Fund | D43: 4 | E43: Unlock | F43: Equity: Large & MidCap | G43: 7.36 | H43: 1 | I43: 16.09 | J43: 9.1 | K43: 16.53 | L43: 12.82 | M43: 1.72 | N43: Very High | O43: Avg. | P43: Direct | Q43: =I43*0.4+K43*0.5 -> 14.701 | R43: =(L43+J43)/2 -> 10.96 | S43: =(M43+K43)/2 -> 9.125 | T43: =('Investor-Inputs'!$G$19 * Q43) + ('Investor-Inputs'!$J$19 * R43) + ('Investor-Inputs'!$N$19 * S43) -> 75.148 | U43: =_xlfn.RANK.EQ(T43,$T$7:$T$592,0) -> 156
C44: UTI Large & Mid Cap Fund - Regular Plan | D44: 5 | E44: Unlock | F44: Equity: Large & MidCap | G44: 6.37 | H44: 2.1 | I44: 20.12 | J44: 10.84 | K44: 17.61 | L44: 15.01 | M44: 1.85 | N44: Very High | O44: Above Avg. | P44: Direct | Q44: =I44*0.4+K44*0.5 -> 16.853 | R44: =(L44+J44)/2 -> 12.925 | S44: =(M44+K44)/2 -> 9.73 | T44: =('Investor-Inputs'!$G$19 * Q44) + ('Investor-Inputs'!$J$19 * R44) + ('Investor-Inputs'!$N$19 * S44) -> 86.139 | U44: =_xlfn.RANK.EQ(T44,$T$7:$T$592,0) -> 106
C45: Aditya Birla Sun Life Flexi Cap Fund - Regular Plan | D45: 4 | E45: Unlock | F45: Equity: Flexi Cap | G45: 6.66 | H45: 2.86 | I45: 17.36 | J45: 10.21 | K45: 13.7 | L45: 12.34 | M45: 1.6 | N45: Very High | O45: Above Avg. | P45: Direct | Q45: =I45*0.4+K45*0.5 -> 13.794 | R45: =(L45+J45)/2 -> 11.275 | S45: =(M45+K45)/2 -> 7.65 | T45: =('Investor-Inputs'!$G$19 * Q45) + ('Investor-Inputs'!$J$19 * R45) + ('Investor-Inputs'!$N$19 * S45) -> 71.582 | U45: =_xlfn.RANK.EQ(T45,$T$7:$T$592,0) -> 186
C46: Bank of India Flexi Cap Fund - Regular Plan | D46: 4 | E46: Unlock | F46: Equity: Flexi Cap | G46: 14.82 | H46: 11.25 | I46: 21.8 | J46: 12.44 | K46: 18.51 | L46: 16.03 | M46: 2.96 | N46: Very High | O46: High | P46: Direct | Q46: =I46*0.4+K46*0.5 -> 17.975 | R46: =(L46+J46)/2 -> 14.235 | S46: =(M46+K46)/2 -> 10.735 | T46: =('Investor-Inputs'!$G$19 * Q46) + ('Investor-Inputs'!$J$19 * R46) + ('Investor-Inputs'!$N$19 * S46) -> 93.13 | U46: =_xlfn.RANK.EQ(T46,$T$7:$T$592,0) -> 71
C47: Canara Robeco Focused Fund - Regular Plan | D47: 4 | E47: Unlock | F47: Equity: Flexi Cap | G47: 1.98 | H47: -6.64 | I47: 14.93 | J47: 6.59 | M47: 2.09 | N47: Very High | O47: Avg. | P47: Direct | Q47: =I47*0.4+K47*0.5 -> 5.972 | R47: =(L47+J47)/2 -> 3.295 | S47: =(M47+K47)/2 -> 1.045 | T47: =('Investor-Inputs'!$G$19 * Q47) + ('Investor-Inputs'!$J$19 * R47) + ('Investor-Inputs'!$N$19 * S47) -> 25.551 | U47: =_xlfn.RANK.EQ(T47,$T$7:$T$592,0) -> 568
C48: Edelweiss Flexi Cap Fund - Regular Plan | D48: 4 | E48: Unlock | F48: Equity: Flexi Cap | G48: 4.73 | H48: -0.41 | I48: 17.16 | J48: 8.55 | K48: 15.17 | L48: 12.36 | M48: 1.92 | N48: Very High | O48: Above Avg. | P48: Direct | Q48: =I48*0.4+K48*0.5 -> 14.449 | R48: =(L48+J48)/2 -> 10.455 | S48: =(M48+K48)/2 -> 8.545 | T48: =('Investor-Inputs'!$G$19 * Q48) + ('Investor-Inputs'!$J$19 * R48) + ('Investor-Inputs'!$N$19 * S48) -> 72.802 | U48: =_xlfn.RANK.EQ(T48,$T$7:$T$592,0) -> 178
C49: Edelweiss Focused Fund - Regular Plan | D49: 4 | E49: Unlock | F49: Equity: Flexi Cap | G49: 2.37 | H49: -2.24 | I49: 15.37 | J49: 6.9 | M49: 2.23 | N49: Very High | O49: Above Avg. | P49: Direct | Q49: =I49*0.4+K49*0.5 -> 6.148 | R49: =(L49+J49)/2 -> 3.45 | S49: =(M49+K49)/2 -> 1.115 | T49: =('Investor-Inputs'!$G$19 * Q49) + ('Investor-Inputs'!$J$19 * R49) + ('Investor-Inputs'!$N$19 * S49) -> 26.459 | U49: =_xlfn.RANK.EQ(T49,$T$7:$T$592,0) -> 564
C50: Franklin India Flexi Cap Fund - Regular Plan | D50: 4 | E50: Unlock | F50: Equity: Flexi Cap | G50: -1.39 | H50: -6.27 | I50: 16 | J50: 5.83 | K50: 15.39 | L50: 11.21 | M50: 1.71 | N50: Very High | O50: Above Avg. | P50: Direct | Q50: =I50*0.4+K50*0.5 -> 14.095 | R50: =(L50+J50)/2 -> 8.52 | S50: =(M50+K50)/2 -> 8.55 | T50: =('Investor-Inputs'!$G$19 * Q50) + ('Investor-Inputs'!$J$19 * R50) + ('Investor-Inputs'!$N$19 * S50) -> 67.875 | U50: =_xlfn.RANK.EQ(T50,$T$7:$T$592,0) -> 198
C51: Franklin India Focused Equity Fund - Regular Plan | D51: 4 | E51: Unlock | F51: Equity: Flexi Cap | G51: -2.84 | H51: -9.87 | I51: 13.16 | J51: 3.34 | K51: 13.83 | L51: 8.99 | M51: 1.88 | N51: Very High | O51: Avg. | P51: Direct | Q51: =I51*0.4+K51*0.5 -> 12.179 | R51: =(L51+J51)/2 -> 6.165 | S51: =(M51+K51)/2 -> 7.855 | T51: =('Investor-Inputs'!$G$19 * Q51) + ('Investor-Inputs'!$J$19 * R51) + ('Investor-Inputs'!$N$19 * S51) -> 56.722 | U51: =_xlfn.RANK.EQ(T51,$T$7:$T$592,0) -> 250
C52: HDFC Flexi Cap Fund - Regular Plan | D52: 5 | E52: Unlock | F52: Equity: Flexi Cap | G52: 1.23 | H52: -4.64 | I52: 18.76 | J52: 9.62 | K52: 19.54 | L52: 15.3 | M52: 1.27 | N52: Very High | O52: High | P52: Direct | Q52: =I52*0.4+K52*0.5 -> 17.274 | R52: =(L52+J52)/2 -> 12.46 | S52: =(M52+K52)/2 -> 10.405 | T52: =('Investor-Inputs'!$G$19 * Q52) + ('Investor-Inputs'!$J$19 * R52) + ('Investor-Inputs'!$N$19 * S52) -> 87.147 | U52: =_xlfn.RANK.EQ(T52,$T$7:$T$592,0) -> 93
C53: HDFC Focused Fund - Regular Plan | D53: 5 | E53: Unlock | F53: Equity: Flexi Cap | G53: 0.44 | H53: -6.25 | I53: 17.86 | J53: 8.88 | K53: 20.23 | L53: 15.12 | M53: 1.6 | N53: Very High | O53: High | P53: Direct | Q53: =I53*0.4+K53*0.5 -> 17.259 | R53: =(L53+J53)/2 -> 12 | S53: =(M53+K53)/2 -> 10.915 | T53: =('Investor-Inputs'!$G$19 * Q53) + ('Investor-Inputs'!$J$19 * R53) + ('Investor-Inputs'!$N$19 * S53) -> 86.692 | U53: =_xlfn.RANK.EQ(T53,$T$7:$T$592,0) -> 96
C54: HDFC Retirement Savings Fund - Equity Plan - Regular Plan | D54: 4 | E54: Unlock | F54: Equity: Flexi Cap | G54: -1.51 | H54: -7.69 | I54: 13.6 | J54: 4.23 | K54: 15.97 | L54: 10.71 | M54: 1.83 | N54: Very High | O54: Avg. | P54: Direct | Q54: =I54*0.4+K54*0.5 -> 13.425 | R54: =(L54+J54)/2 -> 7.47 | S54: =(M54+K54)/2 -> 8.9 | T54: =('Investor-Inputs'!$G$19 * Q54) + ('Investor-Inputs'!$J$19 * R54) + ('Investor-Inputs'!$N$19 * S54) -> 64.115 | U54: =_xlfn.RANK.EQ(T54,$T$7:$T$592,0) -> 214
C55: HSBC Flexi Cap Fund | D55: 4 | E55: Unlock | F55: Equity: Flexi Cap | G55: 8.05 | H55: 3.56 | I55: 18.27 | J55: 9.97 | K55: 15.49 | L55: 13.23 | M55: 2.3 | N55: Very High | O55: Above Avg. | P55: Direct | Q55: =I55*0.4+K55*0.5 -> 15.053 | R55: =(L55+J55)/2 -> 11.6 | S55: =(M55+K55)/2 -> 8.895 | T55: =('Investor-Inputs'!$G$19 * Q55) + ('Investor-Inputs'!$J$19 * R55) + ('Investor-Inputs'!$N$19 * S55) -> 77.254 | U55: =_xlfn.RANK.EQ(T55,$T$7:$T$592,0) -> 148
C56: ICICI Prudential Diversified Equity All Cap Omni FoF | D56: 5 | E56: Unlock | F56: Equity: Flexi Cap | G56: 2.85 | H56: -0.6 | I56: 18.97 | J56: 9.7 | K56: 17.79 | L56: 14.33 | M56: 0.98 | N56: Very High | O56: High | P56: Direct | Q56: =I56*0.4+K56*0.5 -> 16.483 | R56: =(L56+J56)/2 -> 12.015 | S56: =(M56+K56)/2 -> 9.385 | T56: =('Investor-Inputs'!$G$19 * Q56) + ('Investor-Inputs'!$J$19 * R56) + ('Investor-Inputs'!$N$19 * S56) -> 82.864 | U56: =_xlfn.RANK.EQ(T56,$T$7:$T$592,0) -> 118
C57: ICICI Prudential Flexicap Fund | D57: 4 | E57: Unlock | F57: Equity: Flexi Cap | G57: 7.85 | H57: 0.06 | I57: 17.49 | J57: 9.1 | M57: 1.77 | N57: Very High | O57: Above Avg. | P57: Direct | Q57: =I57*0.4+K57*0.5 -> 6.996 | R57: =(L57+J57)/2 -> 4.55 | S57: =(M57+K57)/2 -> 0.885 | T57: =('Investor-Inputs'!$G$19 * Q57) + ('Investor-Inputs'!$J$19 * R57) + ('Investor-Inputs'!$N$19 * S57) -> 30.973 | U57: =_xlfn.RANK.EQ(T57,$T$7:$T$592,0) -> 510
C58: ICICI Prudential Focused Equity Fund | D58: 5 | E58: Unlock | F58: Equity: Flexi Cap | G58: 3.28 | H58: -3.63 | I58: 19.91 | J58: 10.72 | K58: 17.9 | L58: 14.94 | M58: 2.37 | N58: Very High | O58: High | P58: Direct | Q58: =I58*0.4+K58*0.5 -> 16.914 | R58: =(L58+J58)/2 -> 12.83 | S58: =(M58+K58)/2 -> 10.135 | T58: =('Investor-Inputs'!$G$19 * Q58) + ('Investor-Inputs'!$J$19 * R58) + ('Investor-Inputs'!$N$19 * S58) -> 86.537 | U58: =_xlfn.RANK.EQ(T58,$T$7:$T$592,0) -> 100
C59: ICICI Prudential Retirement Fund - Pure Equity Plan | D59: 5 | E59: Unlock | F59: Equity: Flexi Cap | G59: 16.83 | H59: 10.82 | I59: 24.99 | J59: 16.19 | K59: 22.43 | L59: 19.21 | M59: 2.09 | N59: Very High | O59: High | P59: Direct | Q59: =I59*0.4+K59*0.5 -> 21.211 | R59: =(L59+J59)/2 -> 17.7 | S59: =(M59+K59)/2 -> 12.26 | T59: =('Investor-Inputs'!$G$19 * Q59) + ('Investor-Inputs'!$J$19 * R59) + ('Investor-Inputs'!$N$19 * S59) -> 111.293 | U59: =_xlfn.RANK.EQ(T59,$T$7:$T$592,0) -> 27
C60: Invesco India Flexi Cap Fund - Regular Plan | D60: 4 | E60: Unlock | F60: Equity: Flexi Cap | G60: 1.78 | H60: -6.19 | I60: 18.68 | J60: 7.97 | M60: 1.86 | N60: Very High | O60: High | P60: Direct | Q60: =I60*0.4+K60*0.5 -> 7.472 | R60: =(L60+J60)/2 -> 3.985 | S60: =(M60+K60)/2 -> 0.93 | T60: =('Investor-Inputs'!$G$19 * Q60) + ('Investor-Inputs'!$J$19 * R60) + ('Investor-Inputs'!$N$19 * S60) -> 31.316 | U60: =_xlfn.RANK.EQ(T60,$T$7:$T$592,0) -> 508
C61: Invesco India Focused Fund - Regular Plan | D61: 4 | E61: Unlock | F61: Equity: Flexi Cap | G61: -2.85 | H61: -7.26 | I61: 21.28 | J61: 8.11 | K61: 15.82 | L61: 12.98 | M61: 1.89 | N61: Very High | O61: Above Avg. | P61: Direct | Q61: =I61*0.4+K61*0.5 -> 16.422 | R61: =(L61+J61)/2 -> 10.545 | S61: =(M61+K61)/2 -> 8.855 | T61: =('Investor-Inputs'!$G$19 * Q61) + ('Investor-Inputs'!$J$19 * R61) + ('Investor-Inputs'!$N$19 * S61) -> 79.211 | U61: =_xlfn.RANK.EQ(T61,$T$7:$T$592,0) -> 136
C62: ITI Flexi Cap Fund - Regular Plan | D62: 4 | E62: Unlock | F62: Equity: Flexi Cap | G62: 9.97 | H62: 4.39 | I62: 19.84 | J62: 10.02 | M62: 2.52 | N62: Very High | O62: High | P62: Direct | Q62: =I62*0.4+K62*0.5 -> 7.936 | R62: =(L62+J62)/2 -> 5.01 | S62: =(M62+K62)/2 -> 1.26 | T62: =('Investor-Inputs'!$G$19 * Q62) + ('Investor-Inputs'!$J$19 * R62) + ('Investor-Inputs'!$N$19 * S62) -> 35.088 | U62: =_xlfn.RANK.EQ(T62,$T$7:$T$592,0) -> 391
C63: JM Flexicap Fund | D63: 4 | E63: Unlock | F63: Equity: Flexi Cap | G63: -1.05 | H63: -4.02 | I63: 18.45 | J63: 5.13 | K63: 17.33 | L63: 12.93 | M63: 2.58 | N63: Very High | O63: Above Avg. | P63: Direct | Q63: =I63*0.4+K63*0.5 -> 16.045 | R63: =(L63+J63)/2 -> 9.03 | S63: =(M63+K63)/2 -> 9.955 | T63: =('Investor-Inputs'!$G$19 * Q63) + ('Investor-Inputs'!$J$19 * R63) + ('Investor-Inputs'!$N$19 * S63) -> 76.15 | U63: =_xlfn.RANK.EQ(T63,$T$7:$T$592,0) -> 152
C64: Kotak Focused Fund - Regular Plan | D64: 4 | E64: Unlock | F64: Equity: Flexi Cap | G64: 10 | H64: 2.92 | I64: 16.21 | J64: 9.97 | K64: 14.22 | L64: 11.98 | M64: 2.29 | N64: Very High | O64: Avg. | P64: Direct | Q64: =I64*0.4+K64*0.5 -> 13.594 | R64: =(L64+J64)/2 -> 10.975 | S64: =(M64+K64)/2 -> 8.255 | T64: =('Investor-Inputs'!$G$19 * Q64) + ('Investor-Inputs'!$J$19 * R64) + ('Investor-Inputs'!$N$19 * S64) -> 70.987 | U64: =_xlfn.RANK.EQ(T64,$T$7:$T$592,0) -> 188
C65: Mahindra Manulife Focused Fund - Regular Plan | D65: 4 | E65: Unlock | F65: Equity: Flexi Cap | G65: 3.23 | H65: 1.2 | I65: 17.74 | J65: 8.67 | K65: 16.82 | L65: 13.34 | M65: 2.13 | N65: Very High | O65: Above Avg. | P65: Direct | Q65: =I65*0.4+K65*0.5 -> 15.506 | R65: =(L65+J65)/2 -> 11.005 | S65: =(M65+K65)/2 -> 9.475 | T65: =('Investor-Inputs'!$G$19 * Q65) + ('Investor-Inputs'!$J$19 * R65) + ('Investor-Inputs'!$N$19 * S65) -> 78.003 | U65: =_xlfn.RANK.EQ(T65,$T$7:$T$592,0) -> 144
C66: Nippon India Retirement Fund - Wealth Creation Scheme | D66: 4 | E66: Unlock | F66: Equity: Flexi Cap | G66: 2.24 | H66: -1.87 | I66: 16.01 | J66: 6.27 | K66: 14.3 | L66: 10.93 | M66: 2.09 | N66: Very High | O66: Above Avg. | P66: Direct | Q66: =I66*0.4+K66*0.5 -> 13.554 | R66: =(L66+J66)/2 -> 8.6 | S66: =(M66+K66)/2 -> 8.195 | T66: =('Investor-Inputs'!$G$19 * Q66) + ('Investor-Inputs'!$J$19 * R66) + ('Investor-Inputs'!$N$19 * S66) -> 66.057 | U66: =_xlfn.RANK.EQ(T66,$T$7:$T$592,0) -> 204
C67: Parag Parikh Flexi Cap Fund - Regular Plan | D67: 5 | E67: Unlock | F67: Equity: Flexi Cap | G67: 3.77 | H67: -1.46 | I67: 16.83 | J67: 9.27 | K67: 15.85 | L67: 13.27 | M67: 1.36 | N67: Very High | O67: Above Avg. | P67: Direct | Q67: =I67*0.4+K67*0.5 -> 14.657 | R67: =(L67+J67)/2 -> 11.27 | S67: =(M67+K67)/2 -> 8.605 | T67: =('Investor-Inputs'!$G$19 * Q67) + ('Investor-Inputs'!$J$19 * R67) + ('Investor-Inputs'!$N$19 * S67) -> 75.116 | U67: =_xlfn.RANK.EQ(T67,$T$7:$T$592,0) -> 158
C68: SBI Focused Fund | D68: 4 | E68: Unlock | F68: Equity: Flexi Cap | G68: 15.83 | H68: 15.25 | I68: 18.72 | J68: 14.78 | K68: 15.04 | L68: 14.29 | M68: 1.51 | N68: Very High | O68: Above Avg. | P68: Direct | Q68: =I68*0.4+K68*0.5 -> 15.008 | R68: =(L68+J68)/2 -> 14.535 | S68: =(M68+K68)/2 -> 8.275 | T68: =('Investor-Inputs'!$G$19 * Q68) + ('Investor-Inputs'!$J$19 * R68) + ('Investor-Inputs'!$N$19 * S68) -> 82.369 | U68: =_xlfn.RANK.EQ(T68,$T$7:$T$592,0) -> 122
C69: Union Retirement Fund - Regular Plan | D69: 4 | E69: Unlock | F69: Equity: Flexi Cap | G69: 7.5 | H69: 2.77 | I69: 16.7 | J69: 8.59 | M69: 2.42 | N69: Very High | O69: Above Avg. | P69: Direct | Q69: =I69*0.4+K69*0.5 -> 6.68 | R69: =(L69+J69)/2 -> 4.295 | S69: =(M69+K69)/2 -> 1.21 | T69: =('Investor-Inputs'!$G$19 * Q69) + ('Investor-Inputs'!$J$19 * R69) + ('Investor-Inputs'!$N$19 * S69) -> 29.84 | U69: =_xlfn.RANK.EQ(T69,$T$7:$T$592,0) -> 542
C70: WhiteOak Capital Flexi Cap Fund - Regular Plan | D70: 4 | E70: Unlock | F70: Equity: Flexi Cap | G70: 3.73 | H70: -1.94 | I70: 17.63 | J70: 8.34 | M70: 1.92 | N70: Very High | O70: Above Avg. | P70: Direct | Q70: =I70*0.4+K70*0.5 -> 7.052 | R70: =(L70+J70)/2 -> 4.17 | S70: =(M70+K70)/2 -> 0.96 | T70: =('Investor-Inputs'!$G$19 * Q70) + ('Investor-Inputs'!$J$19 * R70) + ('Investor-Inputs'!$N$19 * S70) -> 30.456 | U70: =_xlfn.RANK.EQ(T70,$T$7:$T$592,0) -> 516
C71: Axis Multicap Fund - Regular Plan | D71: 5 | E71: Unlock | F71: Equity: Multi Cap | G71: 7.22 | H71: 1.24 | I71: 21.3 | J71: 10.81 | M71: 2.29 | N71: Very High | O71: High | P71: Direct | Q71: =I71*0.4+K71*0.5 -> 8.52 | R71: =(L71+J71)/2 -> 5.405 | S71: =(M71+K71)/2 -> 1.145 | T71: =('Investor-Inputs'!$G$19 * Q71) + ('Investor-Inputs'!$J$19 * R71) + ('Investor-Inputs'!$N$19 * S71) -> 37.515 | U71: =_xlfn.RANK.EQ(T71,$T$7:$T$592,0) -> 335
C72: Bank of India Multi Cap Fund - Regular Plan | D72: 4 | E72: Unlock | F72: Equity: Multi Cap | G72: 13.77 | H72: 10.51 | I72: 21.12 | J72: 12.49 | M72: 2.24 | N72: Very High | O72: Above Avg. | P72: Direct | Q72: =I72*0.4+K72*0.5 -> 8.448 | R72: =(L72+J72)/2 -> 6.245 | S72: =(M72+K72)/2 -> 1.12 | T72: =('Investor-Inputs'!$G$19 * Q72) + ('Investor-Inputs'!$J$19 * R72) + ('Investor-Inputs'!$N$19 * S72) -> 38.954 | U72: =_xlfn.RANK.EQ(T72,$T$7:$T$592,0) -> 333
C73: HSBC Multi Cap Fund - Regular Plan | D73: 4 | E73: Unlock | F73: Equity: Multi Cap | G73: 9.74 | H73: 5.17 | I73: 22.24 | J73: 11.16 | M73: 2.22 | N73: Very High | O73: High | P73: Direct | Q73: =I73*0.4+K73*0.5 -> 8.896 | R73: =(L73+J73)/2 -> 5.58 | S73: =(M73+K73)/2 -> 1.11 | T73: =('Investor-Inputs'!$G$19 * Q73) + ('Investor-Inputs'!$J$19 * R73) + ('Investor-Inputs'!$N$19 * S73) -> 38.958 | U73: =_xlfn.RANK.EQ(T73,$T$7:$T$592,0) -> 331
C74: ICICI Prudential Multicap Fund | D74: 4 | E74: Unlock | F74: Equity: Multi Cap | G74: 7.74 | H74: 7.85 | I74: 20.31 | J74: 11.44 | K74: 17.83 | L74: 15.16 | M74: 2.02 | N74: Very High | O74: Avg. | P74: Direct | Q74: =I74*0.4+K74*0.5 -> 17.039 | R74: =(L74+J74)/2 -> 13.3 | S74: =(M74+K74)/2 -> 9.925 | T74: =('Investor-Inputs'!$G$19 * Q74) + ('Investor-Inputs'!$J$19 * R74) + ('Investor-Inputs'!$N$19 * S74) -> 87.642 | U74: =_xlfn.RANK.EQ(T74,$T$7:$T$592,0) -> 89
C75: Kotak Multicap Fund - Regular Plan | D75: 5 | E75: Unlock | F75: Equity: Multi Cap | G75: 11.15 | H75: 6.06 | I75: 22.8 | J75: 11.97 | M75: 1.64 | N75: Very High | O75: High | P75: Direct | Q75: =I75*0.4+K75*0.5 -> 9.12 | R75: =(L75+J75)/2 -> 5.985 | S75: =(M75+K75)/2 -> 0.82 | T75: =('Investor-Inputs'!$G$19 * Q75) + ('Investor-Inputs'!$J$19 * R75) + ('Investor-Inputs'!$N$19 * S75) -> 40.15 | U75: =_xlfn.RANK.EQ(T75,$T$7:$T$592,0) -> 325
C76: Mahindra Manulife Multi Cap Fund - Regular Plan | D76: 4 | E76: Unlock | F76: Equity: Multi Cap | G76: 10.06 | H76: 6.32 | I76: 20.36 | J76: 10.59 | K76: 17.84 | L76: 14.39 | M76: 2.91 | N76: Very High | O76: Above Avg. | P76: Direct | Q76: =I76*0.4+K76*0.5 -> 17.064 | R76: =(L76+J76)/2 -> 12.49 | S76: =(M76+K76)/2 -> 10.375 | T76: =('Investor-Inputs'!$G$19 * Q76) + ('Investor-Inputs'!$J$19 * R76) + ('Investor-Inputs'!$N$19 * S76) -> 86.547 | U76: =_xlfn.RANK.EQ(T76,$T$7:$T$592,0) -> 98
C77: Nippon India Multi Cap Fund | D77: 5 | E77: Unlock | F77: Equity: Multi Cap | G77: 7.19 | H77: 1.59 | I77: 20.32 | J77: 9.75 | K77: 21.31 | L77: 16.27 | M77: 1.47 | N77: Very High | O77: Above Avg. | P77: Direct | Q77: =I77*0.4+K77*0.5 -> 18.783 | R77: =(L77+J77)/2 -> 13.01 | S77: =(M77+K77)/2 -> 11.39 | T77: =('Investor-Inputs'!$G$19 * Q77) + ('Investor-Inputs'!$J$19 * R77) + ('Investor-Inputs'!$N$19 * S77) -> 93.759 | U77: =_xlfn.RANK.EQ(T77,$T$7:$T$592,0) -> 63
C78: Edelweiss Mid Cap Fund - Regular Plan | D78: 5 | E78: Unlock | F78: Equity: Mid Cap | G78: 10.73 | H78: 5.67 | I78: 24.72 | J78: 14.67 | K78: 21.02 | L78: 18.48 | M78: 1.8 | N78: Very High | O78: Above Avg. | P78: Direct | Q78: =I78*0.4+K78*0.5 -> 20.398 | R78: =(L78+J78)/2 -> 16.575 | S78: =(M78+K78)/2 -> 11.41 | T78: =('Investor-Inputs'!$G$19 * Q78) + ('Investor-Inputs'!$J$19 * R78) + ('Investor-Inputs'!$N$19 * S78) -> 105.754 | U78: =_xlfn.RANK.EQ(T78,$T$7:$T$592,0) -> 39
C79: HDFC Mid Cap Fund - Regular Plan | D79: 5 | E79: Unlock | F79: Equity: Mid Cap | G79: 10.69 | H79: 2.78 | I79: 23.56 | J79: 12.21 | K79: 21.25 | L79: 18.34 | M79: 1.3 | N79: Very High | O79: Above Avg. | P79: Direct | Q79: =I79*0.4+K79*0.5 -> 20.049 | R79: =(L79+J79)/2 -> 15.275 | S79: =(M79+K79)/2 -> 11.275 | T79: =('Investor-Inputs'!$G$19 * Q79) + ('Investor-Inputs'!$J$19 * R79) + ('Investor-Inputs'!$N$19 * S79) -> 101.972 | U79: =_xlfn.RANK.EQ(T79,$T$7:$T$592,0) -> 45
C80: ICICI Prudential Midcap Fund | D80: 4 | E80: Unlock | F80: Equity: Mid Cap | G80: 24.33 | H80: 19.63 | I80: 26.21 | J80: 18.78 | K80: 20.73 | L80: 19.6 | M80: 1.84 | N80: Very High | O80: Above Avg. | P80: Direct | Q80: =I80*0.4+K80*0.5 -> 20.849 | R80: =(L80+J80)/2 -> 19.19 | S80: =(M80+K80)/2 -> 11.285 | T80: =('Investor-Inputs'!$G$19 * Q80) + ('Investor-Inputs'!$J$19 * R80) + ('Investor-Inputs'!$N$19 * S80) -> 112.212 | U80: =_xlfn.RANK.EQ(T80,$T$7:$T$592,0) -> 25
C81: Invesco India Mid Cap Fund - Regular Plan | D81: 4 | E81: Unlock | F81: Equity: Mid Cap | G81: 13.6 | H81: 4.16 | I81: 25.59 | J81: 16.05 | K81: 21.01 | L81: 19.18 | M81: 2.17 | N81: Very High | O81: High | P81: Direct | Q81: =I81*0.4+K81*0.5 -> 20.741 | R81: =(L81+J81)/2 -> 17.615 | S81: =(M81+K81)/2 -> 11.59 | T81: =('Investor-Inputs'!$G$19 * Q81) + ('Investor-Inputs'!$J$19 * R81) + ('Investor-Inputs'!$N$19 * S81) -> 109.043 | U81: =_xlfn.RANK.EQ(T81,$T$7:$T$592,0) -> 33
C82: ITI Mid Cap Fund - Regular Plan | D82: 4 | E82: Unlock | F82: Equity: Mid Cap | G82: 11.39 | H82: 6.83 | I82: 23.61 | J82: 12.25 | K82: 16.78 | L82: 16.26 | M82: 1.84 | N82: Very High | O82: Above Avg. | P82: Direct | Q82: =I82*0.4+K82*0.5 -> 17.834 | R82: =(L82+J82)/2 -> 14.255 | S82: =(M82+K82)/2 -> 9.31 | T82: =('Investor-Inputs'!$G$19 * Q82) + ('Investor-Inputs'!$J$19 * R82) + ('Investor-Inputs'!$N$19 * S82) -> 91.322 | U82: =_xlfn.RANK.EQ(T82,$T$7:$T$592,0) -> 75
C83: JM Midcap Fund - Regular Plan | D83: 4 | E83: Unlock | F83: Equity: Mid Cap | G83: 7.09 | H83: 3.68 | I83: 23.26 | J83: 10.26 | M83: 2.31 | N83: Very High | O83: Above Avg. | P83: Direct | Q83: =I83*0.4+K83*0.5 -> 9.304 | R83: =(L83+J83)/2 -> 5.13 | S83: =(M83+K83)/2 -> 1.155 | T83: =('Investor-Inputs'!$G$19 * Q83) + ('Investor-Inputs'!$J$19 * R83) + ('Investor-Inputs'!$N$19 * S83) -> 39.327 | U83: =_xlfn.RANK.EQ(T83,$T$7:$T$592,0) -> 329
C84: Kotak Midcap Fund - Regular Plan | D84: 4 | E84: Unlock | F84: Equity: Mid Cap | G84: 13.91 | H84: 6.69 | I84: 21.47 | J84: 13.11 | K84: 18.88 | L84: 16.37 | M84: 1.45 | N84: Very High | O84: Avg. | P84: Direct | Q84: =I84*0.4+K84*0.5 -> 18.028 | R84: =(L84+J84)/2 -> 14.74 | S84: =(M84+K84)/2 -> 10.165 | T84: =('Investor-Inputs'!$G$19 * Q84) + ('Investor-Inputs'!$J$19 * R84) + ('Investor-Inputs'!$N$19 * S84) -> 93.729 | U84: =_xlfn.RANK.EQ(T84,$T$7:$T$592,0) -> 65
C85: Mahindra Manulife Mid Cap Fund - Regular Plan | D85: 4 | E85: Unlock | F85: Equity: Mid Cap | G85: 12.03 | H85: 11.03 | I85: 24.21 | J85: 13.27 | K85: 20.1 | L85: 17.7 | M85: 2.27 | N85: Very High | O85: Above Avg. | P85: Direct | Q85: =I85*0.4+K85*0.5 -> 19.734 | R85: =(L85+J85)/2 -> 15.485 | S85: =(M85+K85)/2 -> 11.185 | T85: =('Investor-Inputs'!$G$19 * Q85) + ('Investor-Inputs'!$J$19 * R85) + ('Investor-Inputs'!$N$19 * S85) -> 101.357 | U85: =_xlfn.RANK.EQ(T85,$T$7:$T$592,0) -> 47
C86: Motilal Oswal Midcap Fund - Regular Plan | D86: 4 | E86: Unlock | F86: Equity: Mid Cap | G86: -3.85 | H86: -12.01 | I86: 20.88 | J86: 6.03 | K86: 22.82 | L86: 15.79 | M86: 1.61 | N86: Very High | O86: High | P86: Direct | Q86: =I86*0.4+K86*0.5 -> 19.762 | R86: =(L86+J86)/2 -> 10.91 | S86: =(M86+K86)/2 -> 12.215 | T86: =('Investor-Inputs'!$G$19 * Q86) + ('Investor-Inputs'!$J$19 * R86) + ('Investor-Inputs'!$N$19 * S86) -> 93.321 | U86: =_xlfn.RANK.EQ(T86,$T$7:$T$592,0) -> 69
C87: Nippon India Growth Mid Cap Fund | D87: 5 | E87: Unlock | F87: Equity: Mid Cap | G87: 12.26 | H87: 8.88 | I87: 25.44 | J87: 14.46 | K87: 22.24 | L87: 19.04 | M87: 1.92 | N87: Very High | O87: High | P87: Direct | Q87: =I87*0.4+K87*0.5 -> 21.296 | R87: =(L87+J87)/2 -> 16.75 | S87: =(M87+K87)/2 -> 12.08 | T87: =('Investor-Inputs'!$G$19 * Q87) + ('Investor-Inputs'!$J$19 * R87) + ('Investor-Inputs'!$N$19 * S87) -> 109.468 | U87: =_xlfn.RANK.EQ(T87,$T$7:$T$592,0) -> 31
C88: Sundaram Mid Cap Fund - Regular Plan | D88: 4 | E88: Unlock | F88: Equity: Mid Cap | G88: 11.3 | H88: 5.56 | I88: 24.15 | J88: 13.44 | K88: 19.86 | L88: 17.61 | M88: 2.25 | N88: Very High | O88: Above Avg. | P88: Direct | Q88: =I88*0.4+K88*0.5 -> 19.59 | R88: =(L88+J88)/2 -> 15.525 | S88: =(M88+K88)/2 -> 11.055 | T88: =('Investor-Inputs'!$G$19 * Q88) + ('Investor-Inputs'!$J$19 * R88) + ('Investor-Inputs'!$N$19 * S88) -> 100.875 | U88: =_xlfn.RANK.EQ(T88,$T$7:$T$592,0) -> 49
C89: WhiteOak Capital Mid Cap Fund - Regular Plan | D89: 5 | E89: Unlock | F89: Equity: Mid Cap | G89: 15.16 | H89: 8.45 | I89: 25.61 | J89: 15.18 | M89: 2.02 | N89: Very High | O89: Above Avg. | P89: Direct | Q89: =I89*0.4+K89*0.5 -> 10.244 | R89: =(L89+J89)/2 -> 7.59 | S89: =(M89+K89)/2 -> 1.01 | T89: =('Investor-Inputs'!$G$19 * Q89) + ('Investor-Inputs'!$J$19 * R89) + ('Investor-Inputs'!$N$19 * S89) -> 46.922 | U89: =_xlfn.RANK.EQ(T89,$T$7:$T$592,0) -> 289
C90: Axis Nifty Smallcap 50 Index Fund - Regular Plan | D90: 4 | E90: Unlock | F90: Equity: Small Cap | G90: 10.08 | H90: 7.41 | I90: 24.27 | J90: 10.89 | M90: 1.05 | N90: Very High | O90: Above Avg. | P90: Direct | Q90: =I90*0.4+K90*0.5 -> 9.708 | R90: =(L90+J90)/2 -> 5.445 | S90: =(M90+K90)/2 -> 0.525 | T90: =('Investor-Inputs'!$G$19 * Q90) + ('Investor-Inputs'!$J$19 * R90) + ('Investor-Inputs'!$N$19 * S90) -> 40.539 | U90: =_xlfn.RANK.EQ(T90,$T$7:$T$592,0) -> 321
C91: Axis Small Cap Fund - Regular Plan | D91: 4 | E91: Unlock | F91: Equity: Small Cap | G91: 8.45 | H91: 4.16 | I91: 17.83 | J91: 8.85 | K91: 18.11 | L91: 13.47 | M91: 1.74 | N91: Very High | O91: Below Avg. | P91: Direct | Q91: =I91*0.4+K91*0.5 -> 16.187 | R91: =(L91+J91)/2 -> 11.16 | S91: =(M91+K91)/2 -> 9.925 | T91: =('Investor-Inputs'!$G$19 * Q91) + ('Investor-Inputs'!$J$19 * R91) + ('Investor-Inputs'!$N$19 * S91) -> 80.806 | U91: =_xlfn.RANK.EQ(T91,$T$7:$T$592,0) -> 128
C92: Bandhan Small Cap Fund - Regular Plan | D92: 5 | E92: Unlock | F92: Equity: Small Cap | G92: 13.73 | H92: 8.68 | I92: 30.4 | J92: 16.61 | K92: 22.81 | L92: 20.73 | M92: 1.98 | N92: Very High | O92: High | P92: Direct | Q92: =I92*0.4+K92*0.5 -> 23.565 | R92: =(L92+J92)/2 -> 18.67 | S92: =(M92+K92)/2 -> 12.395 | T92: =('Investor-Inputs'!$G$19 * Q92) + ('Investor-Inputs'!$J$19 * R92) + ('Investor-Inputs'!$N$19 * S92) -> 120.43 | U92: =_xlfn.RANK.EQ(T92,$T$7:$T$592,0) -> 13
C93: Edelweiss Small Cap Fund - Regular Plan | D93: 4 | E93: Unlock | F93: Equity: Small Cap | G93: 9.75 | H93: 4.15 | I93: 19.04 | J93: 8.69 | K93: 19.37 | L93: 14.24 | M93: 2.13 | N93: Very High | O93: Avg. | P93: Direct | Q93: =I93*0.4+K93*0.5 -> 17.301 | R93: =(L93+J93)/2 -> 11.465 | S93: =(M93+K93)/2 -> 10.75 | T93: =('Investor-Inputs'!$G$19 * Q93) + ('Investor-Inputs'!$J$19 * R93) + ('Investor-Inputs'!$N$19 * S93) -> 85.583 | U93: =_xlfn.RANK.EQ(T93,$T$7:$T$592,0) -> 108
C94: HDFC Small Cap Fund - Regular Plan | D94: 4 | E94: Unlock | F94: Equity: Small Cap | G94: 7.06 | H94: -5.28 | I94: 16.39 | J94: 4.86 | K94: 19.08 | L94: 12.77 | M94: 1.62 | N94: Very High | O94: Above Avg. | P94: Direct | Q94: =I94*0.4+K94*0.5 -> 16.096 | R94: =(L94+J94)/2 -> 8.815 | S94: =(M94+K94)/2 -> 10.35 | T94: =('Investor-Inputs'!$G$19 * Q94) + ('Investor-Inputs'!$J$19 * R94) + ('Investor-Inputs'!$N$19 * S94) -> 76.268 | U94: =_xlfn.RANK.EQ(T94,$T$7:$T$592,0) -> 150
C95: Invesco India Smallcap Fund - Regular Plan | D95: 5 | E95: Unlock | F95: Equity: Small Cap | G95: 11.15 | H95: 5.39 | I95: 24.12 | J95: 12.68 | K95: 21.78 | L95: 17.54 | M95: 1.93 | N95: Very High | O95: High | P95: Direct | Q95: =I95*0.4+K95*0.5 -> 20.538 | R95: =(L95+J95)/2 -> 15.11 | S95: =(M95+K95)/2 -> 11.855 | T95: =('Investor-Inputs'!$G$19 * Q95) + ('Investor-Inputs'!$J$19 * R95) + ('Investor-Inputs'!$N$19 * S95) -> 103.689 | U95: =_xlfn.RANK.EQ(T95,$T$7:$T$592,0) -> 41
C96: ITI Small Cap Fund - Regular Plan | D96: 4 | E96: Unlock | F96: Equity: Small Cap | G96: 12.21 | H96: 10.35 | I96: 25.17 | J96: 13.49 | K96: 17.59 | L96: 17.59 | M96: 1.95 | N96: Very High | O96: Above Avg. | P96: Direct | Q96: =I96*0.4+K96*0.5 -> 18.863 | R96: =(L96+J96)/2 -> 15.54 | S96: =(M96+K96)/2 -> 9.77 | T96: =('Investor-Inputs'!$G$19 * Q96) + ('Investor-Inputs'!$J$19 * R96) + ('Investor-Inputs'!$N$19 * S96) -> 97.439 | U96: =_xlfn.RANK.EQ(T96,$T$7:$T$592,0) -> 55
C97: Kotak Nifty Smallcap 50 Index Fund - Regular Plan | D97: 4 | E97: Unlock | F97: Equity: Small Cap | G97: 9.85 | H97: 7.03 | I97: 24.28 | J97: 10.96 | M97: 1.52 | N97: Very High | O97: Above Avg. | P97: Direct | Q97: =I97*0.4+K97*0.5 -> 9.712 | R97: =(L97+J97)/2 -> 5.48 | S97: =(M97+K97)/2 -> 0.76 | T97: =('Investor-Inputs'!$G$19 * Q97) + ('Investor-Inputs'!$J$19 * R97) + ('Investor-Inputs'!$N$19 * S97) -> 40.856 | U97: =_xlfn.RANK.EQ(T97,$T$7:$T$592,0) -> 315
C98: Mahindra Manulife Small Cap Fund - Regular Plan | D98: 4 | E98: Unlock | F98: Equity: Small Cap | G98: 13.69 | H98: 10.21 | I98: 24.06 | J98: 11.35 | M98: 2.96 | N98: Very High | O98: Above Avg. | P98: Direct | Q98: =I98*0.4+K98*0.5 -> 9.624 | R98: =(L98+J98)/2 -> 5.675 | S98: =(M98+K98)/2 -> 1.48 | T98: =('Investor-Inputs'!$G$19 * Q98) + ('Investor-Inputs'!$J$19 * R98) + ('Investor-Inputs'!$N$19 * S98) -> 41.702 | U98: =_xlfn.RANK.EQ(T98,$T$7:$T$592,0) -> 309
C99: Nippon India Small Cap Fund | D99: 4 | E99: Unlock | F99: Equity: Small Cap | G99: 10.36 | H99: 7.52 | I99: 21.1 | J99: 9.55 | K99: 22.34 | L99: 16.63 | M99: 1.5 | N99: Very High | O99: Above Avg. | P99: Direct | Q99: =I99*0.4+K99*0.5 -> 19.61 | R99: =(L99+J99)/2 -> 13.09 | S99: =(M99+K99)/2 -> 11.92 | T99: =('Investor-Inputs'!$G$19 * Q99) + ('Investor-Inputs'!$J$19 * R99) + ('Investor-Inputs'!$N$19 * S99) -> 96.93 | U99: =_xlfn.RANK.EQ(T99,$T$7:$T$592,0) -> 57
C100: Quant Small Cap Fund | D100: 4 | E100: Unlock | F100: Equity: Small Cap | G100: 8.43 | H100: 7.23 | I100: 20.13 | J100: 8.46 | K100: 21.82 | L100: 15.83 | M100: 2.02 | N100: Very High | O100: High | P100: Direct | Q100: =I100*0.4+K100*0.5 -> 18.962 | R100: =(L100+J100)/2 -> 12.145 | S100: =(M100+K100)/2 -> 11.92 | T100: =('Investor-Inputs'!$G$19 * Q100) + ('Investor-Inputs'!$J$19 * R100) + ('Investor-Inputs'!$N$19 * S100) -> 93.096 | U100: =_xlfn.RANK.EQ(T100,$T$7:$T$592,0) -> 73
C101: Sundaram Small Cap Fund - Regular Plan | D101: 4 | E101: Unlock | F101: Equity: Small Cap | G101: 15.74 | H101: 12.23 | I101: 20.48 | J101: 11.42 | K101: 19.42 | L101: 15.46 | M101: 1.91 | N101: Very High | O101: Avg. | P101: Direct | Q101: =I101*0.4+K101*0.5 -> 17.902 | R101: =(L101+J101)/2 -> 13.44 | S101: =(M101+K101)/2 -> 10.665 | T101: =('Investor-Inputs'!$G$19 * Q101) + ('Investor-Inputs'!$J$19 * R101) + ('Investor-Inputs'!$N$19 * S101) -> 91.251 | U101: =_xlfn.RANK.EQ(T101,$T$7:$T$592,0) -> 77
C102: Axis Value Fund - Regular Plan | D102: 4 | E102: Unlock | F102: Equity: Value Oriented | G102: 7.95 | H102: 2.57 | I102: 20.8 | J102: 10.98 | M102: 2.55 | N102: Very High | O102: Above Avg. | P102: Direct | Q102: =I102*0.4+K102*0.5 -> 8.32 | R102: =(L102+J102)/2 -> 5.49 | S102: =(M102+K102)/2 -> 1.275 | T102: =('Investor-Inputs'!$G$19 * Q102) + ('Investor-Inputs'!$J$19 * R102) + ('Investor-Inputs'!$N$19 * S102) -> 37.215 | U102: =_xlfn.RANK.EQ(T102,$T$7:$T$592,0) -> 339
C103: Bandhan Value Fund - Regular Plan | D103: 4 | E103: Unlock | F103: Equity: Value Oriented | G103: 1.38 | H103: -2.01 | I103: 15.19 | J103: 5.58 | K103: 16.44 | L103: 11.3 | M103: 2.1 | N103: Very High | O103: Avg. | P103: Direct | Q103: =I103*0.4+K103*0.5 -> 14.296 | R103: =(L103+J103)/2 -> 8.44 | S103: =(M103+K103)/2 -> 9.27 | T103: =('Investor-Inputs'!$G$19 * Q103) + ('Investor-Inputs'!$J$19 * R103) + ('Investor-Inputs'!$N$19 * S103) -> 69.038 | U103: =_xlfn.RANK.EQ(T103,$T$7:$T$592,0) -> 194
C104: DSP Value Fund - Regular Plan | D104: 5 | E104: Unlock | F104: Equity: Value Oriented | G104: 15.03 | H104: 10.36 | I104: 19.21 | J104: 13.9 | K104: 15.01 | L104: 15.12 | M104: 1.94 | N104: Very High | O104: Avg. | P104: Direct | Q104: =I104*0.4+K104*0.5 -> 15.189 | R104: =(L104+J104)/2 -> 14.51 | S104: =(M104+K104)/2 -> 8.475 | T104: =('Investor-Inputs'!$G$19 * Q104) + ('Investor-Inputs'!$J$19 * R104) + ('Investor-Inputs'!$N$19 * S104) -> 83.062 | U104: =_xlfn.RANK.EQ(T104,$T$7:$T$592,0) -> 116
C105: HSBC Value Fund | D105: 4 | E105: Unlock | F105: Equity: Value Oriented | G105: 10.09 | H105: 4.37 | I105: 21.67 | J105: 11.81 | K105: 19.47 | L105: 16.66 | M105: 1.71 | N105: Very High | O105: High | P105: Direct | Q105: =I105*0.4+K105*0.5 -> 18.403 | R105: =(L105+J105)/2 -> 14.235 | S105: =(M105+K105)/2 -> 10.59 | T105: =('Investor-Inputs'!$G$19 * Q105) + ('Investor-Inputs'!$J$19 * R105) + ('Investor-Inputs'!$N$19 * S105) -> 94.269 | U105: =_xlfn.RANK.EQ(T105,$T$7:$T$592,0) -> 59
...

Sheet VisualAnalysis
A1: Row Labels | B1: Average of Rank
A2: Bajaj Finserv Overnight Fund - Regular Plan | B2: 585
A3: Canara Robeco Focused Fund - Regular Plan | B3: 568
A4: Edelweiss CRISIL IBX 50:50 Gilt Plus SDL Short Duration Index Fund - Regular Plan | B4: 579
A5: Franklin India Balanced Advantage Fund - Regular Plan | B5: 577
A6: Mirae Asset Balanced Advantage Fund - Regular Plan | B6: 572
A7: Motilal Oswal 5 Year G-Sec FoF - Regular Plan | B7: 581
A8: Parag Parikh Conservative Hybrid Fund - Regular Plan | B8: 575
A9: SBI Balanced Advantage Fund - Regular Plan | B9: 570
A10: Tata Gold ETF FoF - Regular Plan | B10: 583
A11: WhiteOak Capital Large Cap Fund - Regular Plan | B11: 566
A12: Grand Total | B12: 575.6
A27: Top 10 Performance Funds Based on User Inputs
